{"title":"Combined feed","url":"https://factcheckr.github.io/daumnews/all.xml","elements":[{"title":"稅공제액, 현금 지급안 부상···\"기업 붙들 파격 보조금 내놔야\"[이슈&워치] (다음뉴스 ─ 홈)","contents":"경제","link":"https://v.daum.net/v/20240429180559983","retrieved":1714382349295},{"title":"尹·李 만남에도 쟁점 법안 '평행선'... 5월 국회도 '먹구름' (다음뉴스 ─ 홈)","contents":"정치","link":"https://v.daum.net/v/20240429181012089","retrieved":1714382349295},{"title":"[날씨] 전남 해안 다소 강한 비‥남해안 내일 새벽까지 비 (다음뉴스 ─ 홈)","contents":"문화","link":"https://v.daum.net/v/20240429180120869","retrieved":1714382349295},{"title":"중장기전략위원회, \"아동수당 등 통폐합해 '가족수당' 신설해야\" (다음뉴스 ─ 홈)","contents":"경제","link":"https://v.daum.net/v/20240429180108856","retrieved":1714382349296},{"title":"대통령실 \"이재명 민생경제·의료 개혁 중심 논의‥별도 합의문 없어\" (다음뉴스 ─ 홈)","contents":"정치","link":"https://v.daum.net/v/20240429180408951","retrieved":1714382349296},{"title":"MBC '쿠팡블랙리스트' '이종섭 출금' 민언련 보도상 (다음뉴스 ─ 홈)","contents":"사회","link":"https://v.daum.net/v/20240429180111861","retrieved":1714382349296},{"title":"윤, 이재명 '민생지원금'에 \"약자 중심 지원 바람직\" 반대 (다음뉴스 ─ 홈)","contents":"정치","link":"https://v.daum.net/v/20240429181406165","retrieved":1714382349303},{"title":"[자막뉴스] \"이건 자연재해\".. 자식 같은 마늘, 절반을 버려야 (다음뉴스 ─ 홈)","contents":"경제","link":"https://v.daum.net/v/20240429181110110","retrieved":1714382349310},{"title":"손목 ‘저릿’ 손가락 ‘화끈’…손목터널 증후군, 증상과 대처법은? (다음뉴스 ─ 홈)","contents":"문화","link":"https://v.daum.net/v/20240429171450976","retrieved":1714379035512},{"title":"지구의 경고…中 덮친 토네이도, 두바이엔 1년치 비가 하루에 (다음뉴스 ─ 홈)","contents":"사회","link":"https://v.daum.net/v/20240429174825414","retrieved":1714382349312},{"title":"尹대통령-이재명 “의료 개혁 인식 같아…합의 이르진 못해” (다음뉴스 ─ 홈)","contents":"정치","link":"https://v.daum.net/v/20240429171718086","retrieved":1714382349314},{"title":"'내 집' 못 사겠네…\"10억이라더니 14억이 웬말\" 날벼락 (다음뉴스 ─ 홈)","contents":"경제","link":"https://v.daum.net/v/20240429174602304","retrieved":1714382349315},{"title":"[금배지 인터뷰] 4선 서영교 \"서울시장 도전\" (다음뉴스 ─ 홈)","contents":"정치","link":"https://v.daum.net/v/20240429175706687","retrieved":1714382349317},{"title":"경찰, ‘KDDX 사업 비리 의혹’ 관련자 조사 진행 (다음뉴스 ─ 홈)","contents":"사회","link":"https://v.daum.net/v/20240429175455638","retrieved":1714382349318},{"title":"사과 값 당분간 안 잡힐 듯…농림부 “참외는 작년과 비슷할 것” (다음뉴스 ─ 홈)","contents":"경제","link":"https://v.daum.net/v/20240429172506360","retrieved":1714382349320},{"title":"오신환 \"국민의힘, 내부 비판하면 잡혀갈 분위기\"…윤상현 \"뺄셈정치 DNA\" (다음뉴스 ─ 홈)","contents":"정치","link":"https://v.daum.net/v/20240429175956748","retrieved":1714382349321},{"title":"국힘 경기·인천 중진, ‘이철규 원내대표 거론’ 비판 (다음뉴스 ─ 홈)","contents":"정치","link":"https://v.daum.net/v/20240429165110756","retrieved":1714378994451},{"title":"의대교수 집단행동 확산하자…정부, 필수의료 분야 '공정한 보상' 확대 (다음뉴스 ─ 홈)","contents":"사회","link":"https://v.daum.net/v/20240429163140718","retrieved":1714382349324},{"title":"“비트코인 32억원 갈 것”…기요사키, ‘美경제’ 전망했다 (다음뉴스 ─ 홈)","contents":"경제","link":"https://v.daum.net/v/20240429175402600","retrieved":1714382349325},{"title":"\"가족 의혹 정리하고 가시면‥\" 면전 발언에 尹대통령 반응이 [현장영상] (다음뉴스 ─ 홈)","contents":"정치","link":"https://v.daum.net/v/20240429174611315","retrieved":1714382349327},{"title":"학동 참사 철거 공사 수주 위해 금품 건넨 철거업자들…유·무죄 엇갈려 (다음뉴스 ─ 사회 ─ 메인뉴스)","contents":"노컷뉴스","link":"https://v.daum.net/v/20240429181506186","retrieved":1714382357077},{"title":"MBC '쿠팡블랙리스트' '이종섭 출금' 민언련 보도상 (다음뉴스 ─ 사회 ─ 메인뉴스)","contents":"MBC","link":"https://v.daum.net/v/20240429180111861","retrieved":1714382357077},{"title":"하남시 253억 하수시설 추가 LH와 줄다리기…“변동예측 가능했다” (다음뉴스 ─ 사회 ─ 메인뉴스)","contents":"경기일보","link":"https://v.daum.net/v/20240429181145120","retrieved":1714382357078},{"title":"건양대·성대·울산대·조선대…'의대 수업 재개' 또 미뤘다(종합) (다음뉴스 ─ 사회 ─ 메인뉴스)","contents":"뉴시스","link":"https://v.daum.net/v/20240429181142119","retrieved":1714382357079},{"title":"내일도 지역 곳곳 비나 소나기 소식…동해안 동풍 영향 서늘한 날씨 (다음뉴스 ─ 사회 ─ 메인뉴스)","contents":"노컷뉴스","link":"https://v.daum.net/v/20240429180901064","retrieved":1714382357084},{"title":"원주시, 미국 풀러턴 시와 정책 간담회…'컴 온 원주' 활로 모색 (다음뉴스 ─ 사회 ─ 메인뉴스)","contents":"연합뉴스","link":"https://v.daum.net/v/20240429180835055","retrieved":1714382357085},{"title":"전공의 떠나자 '생계 위협' 간병사...월 211만원→110만원으로 줄어 (다음뉴스 ─ 사회 ─ 메이저)","contents":"JTBC","link":"https://v.daum.net/v/20240429180440958","retrieved":1714382364555},{"title":"야구방망이로 채무자 살해한 전 프로선수에 15년형…검찰은 항소 (다음뉴스 ─ 사회 ─ 메이저)","contents":"한국경제","link":"https://v.daum.net/v/20240429173601856","retrieved":1714382364556},{"title":"경찰, ‘KDDX 사업 비리 의혹’ 관련자 조사 진행 (다음뉴스 ─ 사회 ─ 메이저)","contents":"채널A","link":"https://v.daum.net/v/20240429175455638","retrieved":1714382364556},{"title":"\"정치한다더니…\" 광주 시민단체 전 대표 복귀 논란 (다음뉴스 ─ 사회 ─ 메이저)","contents":"연합뉴스","link":"https://v.daum.net/v/20240429175957749","retrieved":1714382364557},{"title":"섬주민에 응급약 배송… 일상 확 달라진다 [뉴스 투데이] (다음뉴스 ─ 사회 ─ 메이저)","contents":"세계일보","link":"https://v.daum.net/v/20240429175550662","retrieved":1714382364558},{"title":"이재명도 증인 신청된 '성남FC 후원금 의혹' 재판…증인만 400명 넘어 (다음뉴스 ─ 사회 ─ 메이저)","contents":"뉴스1","link":"https://v.daum.net/v/20240429175523653","retrieved":1714382364561},{"title":"[취재파일] \"보증금란은 공란으로\"…주택임대관리업체 피해자 속출 (다음뉴스 ─ 사회 ─ 메이저)","contents":"SBS","link":"https://v.daum.net/v/20240429175400592","retrieved":1714382364562},{"title":"전국 교사들 \"제주 불법 촬영 10대 엄벌 탄원\" (다음뉴스 ─ 사회 ─ 메이저)","contents":"뉴시스","link":"https://v.daum.net/v/20240429175317581","retrieved":1714382364564},{"title":"[줌인] 신입직원 5년내 퇴사 31.6%… 근무환경 개선요구 거세 (다음뉴스 ─ 사회 ─ 메이저)","contents":"대전일보","link":"https://v.daum.net/v/20240429175255563","retrieved":1714382364565},{"title":"아이들이 행복하게…가족 나들이 어때요? (다음뉴스 ─ 사회 ─ 메이저)","contents":"한겨레","link":"https://v.daum.net/v/20240429175005475","retrieved":1714382364566},{"title":"대통령실 \"이재명 민생경제·의료 개혁 중심 논의‥별도 합의문 없어\" (다음뉴스 ─ 정치 ─ 메인뉴스)","contents":"MBC","link":"https://v.daum.net/v/20240429180408951","retrieved":1714382372094},{"title":"윤, 이재명 '민생지원금'에 \"약자 중심 지원 바람직\" 반대 (다음뉴스 ─ 정치 ─ 메인뉴스)","contents":"뉴시스","link":"https://v.daum.net/v/20240429181406165","retrieved":1714382372095},{"title":"조국당 \"결과물 초라한 영수회담 암담...윤 대통령 무운을 빈다\" (다음뉴스 ─ 정치 ─ 메인뉴스)","contents":"머니투데이","link":"https://v.daum.net/v/20240429181319151","retrieved":1714382372101},{"title":"[속보] 대통령실 “尹대통령-이재명, 앞으로 종종 만나기로” (다음뉴스 ─ 정치 ─ 메인뉴스)","contents":"중앙일보","link":"https://v.daum.net/v/20240429171817127","retrieved":1714382372102},{"title":"尹·李 만남에도 쟁점 법안 '평행선'... 5월 국회도 '먹구름' (다음뉴스 ─ 정치 ─ 메인뉴스)","contents":"한국일보","link":"https://v.daum.net/v/20240429181012089","retrieved":1714382372104},{"title":"尹대통령-이재명 “의료 개혁 인식 같아…합의 이르진 못해” (다음뉴스 ─ 정치 ─ 메인뉴스)","contents":"국민일보","link":"https://v.daum.net/v/20240429171718086","retrieved":1714382372105},{"title":"‘채 상병 특검’ 다룰 5월 임시국회 개최, 또다시 평행선 (다음뉴스 ─ 정치 ─ 메이저)","contents":"경향신문","link":"https://v.daum.net/v/20240429180456961","retrieved":1714382380119},{"title":"[금배지 인터뷰] 4선 서영교 \"서울시장 도전\" (다음뉴스 ─ 정치 ─ 메이저)","contents":"매일경제","link":"https://v.daum.net/v/20240429175706687","retrieved":1714382380119},{"title":"대통령실 “윤-이, 자주 만나기로…어떤 형식이든 좋아” (다음뉴스 ─ 정치 ─ 메이저)","contents":"채널A","link":"https://v.daum.net/v/20240429173054644","retrieved":1714382380119},{"title":"박지원 \"추미애 1등, 나 2등..국회의장, '명심'보단 이걸 잘 봐야\"[여의도초대석] (다음뉴스 ─ 정치 ─ 메이저)","contents":"kbc광주방송","link":"https://v.daum.net/v/20240429180056846","retrieved":1714382380120},{"title":"오신환 \"국민의힘, 내부 비판하면 잡혀갈 분위기\"…윤상현 \"뺄셈정치 DNA\" (다음뉴스 ─ 정치 ─ 메이저)","contents":"프레시안","link":"https://v.daum.net/v/20240429175956748","retrieved":1714382380121},{"title":"\"가족 의혹 정리하고 가시면‥\" 면전 발언에 尹대통령 반응이 [현장영상] (다음뉴스 ─ 정치 ─ 메이저)","contents":"MBC","link":"https://v.daum.net/v/20240429174611315","retrieved":1714382380123},{"title":"민주 \"尹, 이태원특별법 거부…가족 의혹 정리 요구에 답 없었다\" (다음뉴스 ─ 정치 ─ 메이저)","contents":"뉴스1","link":"https://v.daum.net/v/20240429175941746","retrieved":1714382380125},{"title":"더불어민주당, 영수회담 결과 브리핑 (다음뉴스 ─ 정치 ─ 메이저)","contents":"MBC","link":"https://v.daum.net/v/20240429174608314","retrieved":1714382380126},{"title":"민주당 “영수회담 큰 기대 했지만, 변화 없었다” (다음뉴스 ─ 정치 ─ 메이저)","contents":"국민일보","link":"https://v.daum.net/v/20240429174029061","retrieved":1714382380128},{"title":"'식량난' 북한, 러시아와 농업 협력 강화…밀 종자 도입 (다음뉴스 ─ 정치 ─ 메이저)","contents":"연합뉴스","link":"https://v.daum.net/v/20240429175422623","retrieved":1714382380129},{"title":"하이브-민희진, 주주간 계약 보니… ‘어도어 지분 가치 산정’이 갈등 원인 (다음뉴스 ─ 경제 ─ 메인뉴스)","contents":"동아일보","link":"https://v.daum.net/v/20240429181511191","retrieved":1714382387664},{"title":"중장기전략위원회, \"아동수당 등 통폐합해 '가족수당' 신설해야\" (다음뉴스 ─ 경제 ─ 메인뉴스)","contents":"MBC","link":"https://v.daum.net/v/20240429180108856","retrieved":1714382387664},{"title":"또 공개매수 직전 급등 … 개미 울리는 미공개정보 유출 (다음뉴스 ─ 경제 ─ 메인뉴스)","contents":"한국경제","link":"https://v.daum.net/v/20240429181304146","retrieved":1714382387669},{"title":"[자막뉴스] \"이건 자연재해\".. 자식 같은 마늘, 절반을 버려야 (다음뉴스 ─ 경제 ─ 메인뉴스)","contents":"JIBS","link":"https://v.daum.net/v/20240429181110110","retrieved":1714382387670},{"title":"稅공제액, 현금 지급안 부상···\"기업 붙들 파격 보조금 내놔야\"[이슈&워치] (다음뉴스 ─ 경제 ─ 메인뉴스)","contents":"서울경제","link":"https://v.daum.net/v/20240429180559983","retrieved":1714382387672},{"title":"사과 값 당분간 안 잡힐 듯…농림부 “참외는 작년과 비슷할 것” (다음뉴스 ─ 경제 ─ 메인뉴스)","contents":"한겨레","link":"https://v.daum.net/v/20240429172506360","retrieved":1714382387674},{"title":"中 '보복관세' 법제화로 미국에 맞불…韓 경제 영향은 (다음뉴스 ─ 경제 ─ 메이저)","contents":"중앙일보","link":"https://v.daum.net/v/20240429180100850","retrieved":1714382394829},{"title":"“비트코인 32억원 갈 것”…기요사키, ‘美경제’ 전망했다 (다음뉴스 ─ 경제 ─ 메이저)","contents":"서울신문","link":"https://v.daum.net/v/20240429175402600","retrieved":1714382394831},{"title":"'가족친화기업' 정부인증 받아도 고작 출입국 우대·건강지원 뿐 (다음뉴스 ─ 경제 ─ 메이저)","contents":"매일경제","link":"https://v.daum.net/v/20240429175714694","retrieved":1714382394833},{"title":"노동인력 절벽 코앞…유학생 구직비자 만들어 외국인 수혈을 (다음뉴스 ─ 경제 ─ 메이저)","contents":"매일경제","link":"https://v.daum.net/v/20240429175712693","retrieved":1714382394835},{"title":"“의지·열정·끈기로 꼭 해내겠다” 이재용의 외침…삼성 ‘1등 꿈’ 실현 가능성은? [김민지의 칩만사!] (다음뉴스 ─ 경제 ─ 메이저)","contents":"헤럴드경제","link":"https://v.daum.net/v/20240429175704683","retrieved":1714382394838},{"title":"[감정평가] 종전자산평가 이의신청, 현명한 접근 필요 (다음뉴스 ─ 경제 ─ 메이저)","contents":"머니투데이","link":"https://v.daum.net/v/20240429175656674","retrieved":1714382394840},{"title":"日·中 경제 영향 받는 韓···원화가치 더 떨어질 듯 (다음뉴스 ─ 경제 ─ 메이저)","contents":"서울경제","link":"https://v.daum.net/v/20240429175049496","retrieved":1714382394841},{"title":"에어부산 임금 감소·인력 유출 심각…어쩌나 (다음뉴스 ─ 경제 ─ 메이저)","contents":"뉴시스","link":"https://v.daum.net/v/20240429174930461","retrieved":1714382394842},{"title":"[생생플러스]  5월 2일은 '오이데이'... 가격도 싸네요? (다음뉴스 ─ 경제 ─ 메이저)","contents":"YTN","link":"https://v.daum.net/v/20240429174908454","retrieved":1714382394844},{"title":"'내 집' 못 사겠네…\"10억이라더니 14억이 웬말\" 날벼락 (다음뉴스 ─ 경제 ─ 메이저)","contents":"한국경제","link":"https://v.daum.net/v/20240429174602304","retrieved":1714382394845},{"title":"[현장영상] ‘검사 배지’ 보여주며 “멍청이”…단속 경찰에게 막말한 검사 논란 (다음뉴스 ─ 국제 ─ 메인뉴스)","contents":"KBS","link":"https://v.daum.net/v/20240429181245142","retrieved":1714382402106},{"title":"한국전 때 박힌 파편과 73년…美 노병에 뒤늦은 퍼플하트 훈장 (다음뉴스 ─ 국제 ─ 메인뉴스)","contents":"아시아경제","link":"https://v.daum.net/v/20240429180924080","retrieved":1714382402107},{"title":"이스라엘 라파 공습으로 생후 5일 아기 등 22명 사망 (다음뉴스 ─ 국제 ─ 메인뉴스)","contents":"뉴시스","link":"https://v.daum.net/v/20240429180429957","retrieved":1714382402109},{"title":"테슬라, 자율주행·AI 드라이브···실적 반등할까 (다음뉴스 ─ 국제 ─ 메인뉴스)","contents":"서울경제","link":"https://v.daum.net/v/20240429175549660","retrieved":1714382402110},{"title":"美 장기 기준금리 4%대 고착하나···‘중립금리 상승’ 논쟁 확산 (다음뉴스 ─ 국제 ─ 메인뉴스)","contents":"서울경제","link":"https://v.daum.net/v/20240429175152543","retrieved":1714382402113},{"title":"경제 침체·뒷돈에··· 자리 위태로운 세계 지도자들 (다음뉴스 ─ 국제 ─ 메인뉴스)","contents":"서울경제","link":"https://v.daum.net/v/20240429175034490","retrieved":1714382402114},{"title":"이번주 FOMC가 '슈퍼엔저' 분수령 (다음뉴스 ─ 국제 ─ 메이저)","contents":"매일경제","link":"https://v.daum.net/v/20240429180604992","retrieved":1714382409309},{"title":"亞 \"자국 통화 지키자\"···印·印尼 등 적극 개입 (다음뉴스 ─ 국제 ─ 메이저)","contents":"서울경제","link":"https://v.daum.net/v/20240429174938465","retrieved":1714382409311},{"title":"우크라 \"텔레그램, 공식 봇 계정 부당하게 차단\" (다음뉴스 ─ 국제 ─ 메이저)","contents":"연합뉴스","link":"https://v.daum.net/v/20240429174852446","retrieved":1714382409312},{"title":"美 '3고' 현상에 엔화 매도 확산···日정부 개입 효과도 '미지수' (다음뉴스 ─ 국제 ─ 메이저)","contents":"서울경제","link":"https://v.daum.net/v/20240429174714343","retrieved":1714382409316},{"title":"中, '日국회의원 센카쿠열도 조사' 항의…\"도발 중단하라\" (다음뉴스 ─ 국제 ─ 메이저)","contents":"연합뉴스","link":"https://v.daum.net/v/20240429174544297","retrieved":1714382409318},{"title":"마크롱 '佛핵우산 유럽 확장' 제안 후폭풍…야권 \"주권 포기\" (다음뉴스 ─ 국제 ─ 메이저)","contents":"뉴시스","link":"https://v.daum.net/v/20240429174328176","retrieved":1714382409319},{"title":"\"尹, 한미일 협력 지속시켜야···G8 가입 등 통큰 외교전략 필요\" (다음뉴스 ─ 국제 ─ 메이저)","contents":"서울경제","link":"https://v.daum.net/v/20240429174051076","retrieved":1714382409321},{"title":"미·일 금리차에 매도 몰렸다…“엔저, 일본 국력 저하가 근본 원인” (다음뉴스 ─ 국제 ─ 메이저)","contents":"한겨레","link":"https://v.daum.net/v/20240429174030063","retrieved":1714382409323},{"title":"중국군, 몽골군과 월말부터 첫 연합훈련 실시 (다음뉴스 ─ 국제 ─ 메이저)","contents":"뉴시스","link":"https://v.daum.net/v/20240429173328771","retrieved":1714382409324},{"title":"\"중국 의존 줄이자\" 일-EU, 경제안보 강화 첫 공동구상 내놓는다 (다음뉴스 ─ 국제 ─ 메이저)","contents":"중앙일보","link":"https://v.daum.net/v/20240429173059647","retrieved":1714382409326},{"title":"[DMA콜렉션] 이남규 'Work' (다음뉴스 ─ 문화 ─ 메인뉴스)","contents":"대전일보","link":"https://v.daum.net/v/20240429175343588","retrieved":1714382417067},{"title":"간송미술관 ‘보화각’ 돌아왔다…\"1500원에 설계\" 86년전 친필 기록도 (다음뉴스 ─ 문화 ─ 메인뉴스)","contents":"중앙일보","link":"https://v.daum.net/v/20240429174454237","retrieved":1714382417067},{"title":"[영상] \"민씨방씨 싸움 어떻게 되든\"…뉴진스 신곡 조회수 '1천300만' (다음뉴스 ─ 문화 ─ 메인뉴스)","contents":"연합뉴스","link":"https://v.daum.net/v/20240429173518838","retrieved":1714382417070},{"title":"간송미술관 설계자는 박길룡이 맞았다…도면 발견 (다음뉴스 ─ 문화 ─ 메인뉴스)","contents":"한겨레","link":"https://v.daum.net/v/20240429172512364","retrieved":1714382417072},{"title":"손목 ‘저릿’ 손가락 ‘화끈’…손목터널 증후군, 증상과 대처법은? (다음뉴스 ─ 문화 ─ 메인뉴스)","contents":"농민신문","link":"https://v.daum.net/v/20240429171450976","retrieved":1714379035512},{"title":"돌아온 성북동 간송미술관 전시…레트로풍 통할까 (다음뉴스 ─ 문화 ─ 메인뉴스)","contents":"국민일보","link":"https://v.daum.net/v/20240429171008790","retrieved":1714379035513},{"title":"손톱 깎으려고 보니 발톱은 그대로… 이유 뭘까? (다음뉴스 ─ 문화 ─ 메이저)","contents":"헬스조선","link":"https://v.daum.net/v/20240429170857744","retrieved":1714379035515},{"title":"중년에 ‘납작 엉덩이’...알고보니 '이런 습관' 때문? (다음뉴스 ─ 문화 ─ 메이저)","contents":"코메디닷컴","link":"https://v.daum.net/v/20240429170605623","retrieved":1714378957767},{"title":"'술 한잔에 농익는 우리 가락'…국립국악관현악단 '애주가' 공연 (다음뉴스 ─ 문화 ─ 메이저)","contents":"연합뉴스","link":"https://v.daum.net/v/20240429165329867","retrieved":1714379035519},{"title":"아이·어른 모두 ‘심장이 쫄깃’··· 5월 서커스 어디서 즐길까 (다음뉴스 ─ 문화 ─ 메이저)","contents":"서울경제","link":"https://v.daum.net/v/20240429164800615","retrieved":1714379035521},{"title":"지혜로운 중년이여, 욕망을 디톡스하라 (다음뉴스 ─ 문화 ─ 메이저)","contents":"한겨레21","link":"https://v.daum.net/v/20240429163801053","retrieved":1714379043486},{"title":"서울 간송미술관 1년7개월만에 재개관…미공개 서화유물 전시 (다음뉴스 ─ 문화 ─ 메이저)","contents":"연합뉴스","link":"https://v.daum.net/v/20240429162919560","retrieved":1714379043489},{"title":"\"고사리 캐러 갔다가 구토·설사\"…야외활동 시 진드기 주의 (다음뉴스 ─ 문화 ─ 메이저)","contents":"강원도민일보","link":"https://v.daum.net/v/20240429145249223","retrieved":1714379043490},{"title":"사람도 소도 행복하지 않은 소싸움... \"올해가 마지막이길\" (다음뉴스 ─ 문화 ─ 메이저)","contents":"한국일보","link":"https://v.daum.net/v/20240429160030291","retrieved":1714375052897},{"title":"고령 만성질환자, OO과 함께 살아야 ‘약’ 잘 챙겨 먹는다 (다음뉴스 ─ 문화 ─ 메이저)","contents":"농민신문","link":"https://v.daum.net/v/20240429155155849","retrieved":1714375052899},{"title":"공간으로 삶을 바꾼 거장의 일대기…노먼 포스터 亞 최대 개인전 (다음뉴스 ─ 문화 ─ 메이저)","contents":"매일경제","link":"https://v.daum.net/v/20240429153604052","retrieved":1714375052900},{"title":"방심위, '김건희 여사 주가조작' 인용보도한 YTN에 경고 확정 (다음뉴스 ─ IT ─ 메인뉴스)","contents":"뉴스1","link":"https://v.daum.net/v/20240429180335926","retrieved":1714382432427},{"title":"2억km 떨어진 우주서 파일 전송했더니...\"광대역 속도\" (다음뉴스 ─ IT ─ 메인뉴스)","contents":"지디넷코리아","link":"https://v.daum.net/v/20240429145134166","retrieved":1714382432428},{"title":"우크라 \"텔레그램, 공식 봇 계정 부당하게 차단\" (다음뉴스 ─ IT ─ 메인뉴스)","contents":"연합뉴스","link":"https://v.daum.net/v/20240429174852446","retrieved":1714382432429},{"title":"‘자연의 간벌꾼’ 딱따구리, 도시로 다시 불러오려면··· (다음뉴스 ─ IT ─ 메인뉴스)","contents":"경향신문","link":"https://v.daum.net/v/20240429173632892","retrieved":1714382432431},{"title":"이통3사 담합의혹...'兆 단위' 과징금 비상 (다음뉴스 ─ IT ─ 메인뉴스)","contents":"전자신문","link":"https://v.daum.net/v/20240429155235877","retrieved":1714382432432},{"title":"물류로 전선 넓힌 미중무역전쟁…韓에 견제동참 요구 가능성↑ (다음뉴스 ─ IT ─ 메인뉴스)","contents":"이데일리","link":"https://v.daum.net/v/20240429171138839","retrieved":1714378985051},{"title":"로봇도 어린아이처럼 넘어지면서 배운다 (다음뉴스 ─ IT ─ 메이저)","contents":"지디넷코리아","link":"https://v.daum.net/v/20240429170726692","retrieved":1714378957765},{"title":"과총, \"내년 '우주연구프로그램' 한국 유치 내달 결론\" (다음뉴스 ─ IT ─ 메이저)","contents":"지디넷코리아","link":"https://v.daum.net/v/20240429164135281","retrieved":1714379051093},{"title":"‘하늘길 뚫기 전쟁’ 통신3사 혈투…미래 기술 가장 앞선 곳 ‘어디’ (다음뉴스 ─ IT ─ 메이저)","contents":"매일경제","link":"https://v.daum.net/v/20240429161203881","retrieved":1714379051097},{"title":"레이 오지의 플로피에서 발견된 MS-DOS 4.0 코드 공개 (다음뉴스 ─ IT ─ 메이저)","contents":"지디넷코리아","link":"https://v.daum.net/v/20240429160737696","retrieved":1714374970902},{"title":"과징금이 조 단위?…판매장려금 담합의혹에 통신3사 불안감 (다음뉴스 ─ IT ─ 메이저)","contents":"머니투데이","link":"https://v.daum.net/v/20240429155002742","retrieved":1714375069255},{"title":"\"새 아이패드, 애플 첫 AI 기기 될 것\"… 관례 깬 공개시간의 비밀은? (다음뉴스 ─ IT ─ 메이저)","contents":"한국일보","link":"https://v.daum.net/v/20240429153234872","retrieved":1714375069256},{"title":"'1조원' 꿈의 현미경 방사광가속기 지연···\"7월말께 설계 완성\" (다음뉴스 ─ IT ─ 메이저)","contents":"이데일리","link":"https://v.daum.net/v/20240429153139814","retrieved":1714375069258},{"title":"배순민 KT 상무 “AI 안전·신뢰성 확보에 투자 늘려야” (다음뉴스 ─ IT ─ 메이저)","contents":"전자신문","link":"https://v.daum.net/v/20240429140939411","retrieved":1714375069260},{"title":"윤 대통령-이재명 대표 첫 회동...의료계 “의대 증원 해결 실마리 기대” (다음뉴스 ─ IT ─ 메이저)","contents":"조선비즈","link":"https://v.daum.net/v/20240429151838305","retrieved":1714371990728},{"title":"LG-카카오 전기차 충전 맞손, 찻잔 넘어서는 태풍 될까 (다음뉴스 ─ IT ─ 메이저)","contents":"머니투데이","link":"https://v.daum.net/v/20240429150744927","retrieved":1714372063991},{"title":"세종시·영국 벨파스트시 경제협력 로드맵 협약 체결 (다음뉴스 ─ 포토)","contents":"지자체 제공 포토","link":"https://gallery.v.daum.net/p/viewer/5847810/zDaNn8Ulu8","retrieved":1714382448046},{"title":"이준석 대표와 환담하는 이철우 경북도지사 (다음뉴스 ─ 포토)","contents":"머니S포토","link":"https://gallery.v.daum.net/p/viewer/5612596/2VZcKFSgfl","retrieved":1714382448048},{"title":"충북대 의대 증원 결정 회의 항의하는 의대 교수와 학생들 (다음뉴스 ─ 포토)","contents":"의대 정원 확대","link":"https://gallery.v.daum.net/p/viewer/5932052/7svTIjxp7c","retrieved":1714382448050},{"title":"尹 앞에서 A4 용지 꺼낸 이재명 대표[청계천 옆 사진관] (다음뉴스 ─ 포토)","contents":"청계천 옆 사진관","link":"https://gallery.v.daum.net/p/viewer/344179/BU5zYZIimK","retrieved":1714382448051},{"title":"개회사하는 정인교 산업통상자원부 통상교섭본부장 (다음뉴스 ─ 포토)","contents":"정부 부처 제공 포토","link":"https://gallery.v.daum.net/p/viewer/321090/8dvmig6FVQ","retrieved":1714382448053},{"title":"맨발의 청춘 (다음뉴스 ─ 포토)","contents":"포토에세이","link":"https://gallery.v.daum.net/p/viewer/5750948/YIE6CvkPLx","retrieved":1714382448054},{"title":"'유럽 예∼' 조지아 친러정부 반대시위 확산 (다음뉴스 ─ 포토)","contents":"조지아는 지금","link":"https://gallery.v.daum.net/p/viewer/5029623/7MZznaP3UC","retrieved":1714379066939},{"title":"첫 영수회담 마친 윤 대통령과 이재명 대표 (다음뉴스 ─ 포토)","contents":"대한민국 대통령실","link":"https://gallery.v.daum.net/p/viewer/1682593/tubZOlA82l","retrieved":1714379066941},{"title":"블링컨, GCC 사무국서 사우디 외교 회담 (다음뉴스 ─ 포토)","contents":"세계의 외교현장","link":"https://gallery.v.daum.net/p/viewer/1013249/WLq1CvkP3K","retrieved":1714379066951},{"title":"조희연 교육감, 학생인권조례 폐지 규탄 천막농성 (다음뉴스 ─ 포토)","contents":"오마이포토","link":"https://gallery.v.daum.net/p/viewer/5615618/4KQIJo8tDm","retrieved":1714379066951},{"title":"세계 동요를 만나는 국립 세계문자박물관 기획특별전 [포토뉴스] (다음뉴스 ─ 포토)","contents":"포토뉴스","link":"https://gallery.v.daum.net/p/viewer/5840500/zfzihTEQTO","retrieved":1714379066952},{"title":"유월절  의식 올리는 사마리아인 (다음뉴스 ─ 포토)","contents":"팔레스타인은 지금","link":"https://gallery.v.daum.net/p/viewer/5032907/1uLhFUWApU","retrieved":1714379066954},{"title":"720일 만의 영수회담, '협치 불씨 살릴까?' (다음뉴스 ─ 포토)","contents":"뉴스1 PICK","link":"https://gallery.v.daum.net/p/viewer/5615616/b4bG10TNpF","retrieved":1714379066957},{"title":"남해소방서 현장대원들과 간담회 하는 남화영 소방청장 (다음뉴스 ─ 포토)","contents":"소방본부 제공 포토","link":"https://gallery.v.daum.net/p/viewer/386/7fJzTGmeu7","retrieved":1714375085113},{"title":"'도뷔시' 시사회 참석한 우크라이나 대사 \"한국 국민들 인도주의적 지원에 감사\" [TF사진관] (다음뉴스 ─ 포토)","contents":"TF사진관","link":"https://gallery.v.daum.net/p/viewer/5024184/2zzdhTEQ0a","retrieved":1714372083302},{"title":"친팔레스타인 시위 벌이는 정통유대인 (다음뉴스 ─ 포토)","contents":"미국은 지금","link":"https://gallery.v.daum.net/p/viewer/1476/4IkeCvkP7C","retrieved":1714375085117},{"title":"'성공적인 한-아프리카 정상회의 개최를 위해' (다음뉴스 ─ 포토)","contents":"세계의 정상들","link":"https://gallery.v.daum.net/p/viewer/1471/p26110TN7g","retrieved":1714372083305},{"title":"우회전하던 SUV가 상가로 돌진…20대 만취 운전자 검거 (다음뉴스 ─ 포토)","contents":"경찰 제공 포토","link":"https://gallery.v.daum.net/p/viewer/1075022/5jkPJo8tw2","retrieved":1714372083307},{"title":"모천 찾아왔지만…장애물 만난 황어 (다음뉴스 ─ 포토)","contents":"모멘트","link":"https://gallery.v.daum.net/p/viewer/5610796/xqaWXtlop3","retrieved":1714372083308},{"title":"싱싱한 악어 팝니다…활력찬 콩고 시장 (다음뉴스 ─ 포토)","contents":"방글라데시는 지금","link":"https://gallery.v.daum.net/p/viewer/5849928/0ph21xqyFY","retrieved":1714368024505},{"title":"[고침] 국제(한은총재 \"중동 확전 않는다면 환율…) (다음뉴스 ─ 언론사 고침기사)","contents":"연합뉴스","link":"https://v.daum.net/v/20240420111752559","retrieved":1713571200000},{"title":"[바로잡습니다] 4월 13일자 24면 ‘22대 국회 초선 의원님들, 등원 전에 이 책만은 꼭’ 기사 (다음뉴스 ─ 언론사 고침기사)","contents":"중앙SUNDAY","link":"https://v.daum.net/v/20240420000128643","retrieved":1713484800000},{"title":"[바로잡습니다] 4월 5일 자 A12면 ‘일본 법원의 ‘품위 손상 판사’ 대처법’ 기사 내 ‘일본의 재판관 탄핵 재판소’ 키워드 중 (다음뉴스 ─ 언론사 고침기사)","contents":"조선일보","link":"https://v.daum.net/v/20240406035544066","retrieved":1712275200000},{"title":"[바로잡습니다] 3월30일 자 A2면 “‘與 보면 가슴 답답’ 보수층 입 닫았다” 기사에서 외 (다음뉴스 ─ 언론사 고침기사)","contents":"조선일보","link":"https://v.daum.net/v/20240403030519807","retrieved":1712016000000},{"title":"[바로잡습니다] 25일 자 A12면 ‘내년 최저임금 1만원 넘을까’ 기사 중 외 (다음뉴스 ─ 언론사 고침기사)","contents":"조선일보","link":"https://v.daum.net/v/20240328030210523","retrieved":1711497600000},{"title":"[고침] 그래픽(4·10 총선 국민의힘·민주당 자체 분석...) (다음뉴스 ─ 언론사 고침기사)","contents":"연합뉴스","link":"https://v.daum.net/v/20240326155226886","retrieved":1711411200000},{"title":"[바로잡습니다] 21일 자 C1면 ‘중동의 큰손들 잇따라 방한… ‘K방산’ 글로벌 4위 청신호’ 기사 중 (다음뉴스 ─ 언론사 고침기사)","contents":"조선일보","link":"https://v.daum.net/v/20240323030511076","retrieved":1711065600000},{"title":"[바로잡습니다] ‘조국 “조국혁신당 인기 이유? 尹 싫은데 민주당도 싫어서”’ 관련 (다음뉴스 ─ 언론사 고침기사)","contents":"중앙일보","link":"https://v.daum.net/v/20240322144019699","retrieved":1711065600000},{"title":"[바로잡습니다] 18일 자 A10면 ‘국내 스타트업 14곳 “오픈 AI 잡아라” 7분씩 사업 소개’ 기사에서 외 (다음뉴스 ─ 언론사 고침기사)","contents":"조선일보","link":"https://v.daum.net/v/20240320032438502","retrieved":1710806400000},{"title":"[바로잡습니다] 12일 자 A2면 ‘스웨덴 입양아… 10년 전 스웨덴 나토 가입 예견’ 기사 중 외 (다음뉴스 ─ 언론사 고침기사)","contents":"조선일보","link":"https://v.daum.net/v/20240314035525251","retrieved":1710288000000},{"title":"[바로잡습니다] 11일 자 A3면 ‘포스코 상생어린이집’ 그래픽에서 외 (다음뉴스 ─ 언론사 고침기사)","contents":"조선일보","link":"https://v.daum.net/v/20240313030427512","retrieved":1710201600000},{"title":"[바로잡습니다] 3월 4일자 B7면 ‘바둑 해설’ 기사 (다음뉴스 ─ 언론사 고침기사)","contents":"중앙일보","link":"https://v.daum.net/v/20240308001132762","retrieved":1709769600000},{"title":"[고침] 그래픽(서울 주요 상권 통상임대료·월평균 매출액) (다음뉴스 ─ 언론사 고침기사)","contents":"연합뉴스","link":"https://v.daum.net/v/20240307081118182","retrieved":1709683200000},{"title":"[바로잡습니다] 4일 자 A12면 ‘쇼핑몰만 8번 도는 ‘덤핑 관광’… 서울시, 제재 추진’ 기사에서 외 (다음뉴스 ─ 언론사 고침기사)","contents":"조선일보","link":"https://v.daum.net/v/20240306030016793","retrieved":1709596800000},{"title":"[바로잡습니다] 17일자 B5면 ‘지우다 못해 조작까지 해서 없애버리는 이승만의 흔적’ 기사 중 (다음뉴스 ─ 언론사 고침기사)","contents":"조선일보","link":"https://v.daum.net/v/20240228032937217","retrieved":1708992000000},{"title":"[바로잡습니다] 14일 자 A8면 〈개혁신당 첫 최고위 이원욱 경기도 화성 조응천 남양주 출마〉 기사에서 (다음뉴스 ─ 언론사 고침기사)","contents":"조선일보","link":"https://v.daum.net/v/20240217034049193","retrieved":1708041600000},{"title":"[바로잡습니다] 13일 자 A10면 ‘HD현대重 울산조선소서 근로자 1명 사망’ 기사 중 (다음뉴스 ─ 언론사 고침기사)","contents":"조선일보","link":"https://v.daum.net/v/20240216035644975","retrieved":1707955200000},{"title":"[추후보도] 2017. 2. 27.자 「합격자 뒤바꾼 대안학교 교장 파면 요구」 보도 관련 (다음뉴스 ─ 언론중재법 피해구제보도)","contents":"YTN","link":"https://v.daum.net/v/20240429093708936","retrieved":1714348800000},{"title":"[반론보도] ＜방심위, ‘부산저축은행 봐주기 의혹’ 보도 기자 출연 MBC라디오 법정제재＞ 관련 (다음뉴스 ─ 언론중재법 피해구제보도)","contents":"KBS","link":"https://v.daum.net/v/20240426230135150","retrieved":1714089600000},{"title":"[반론보도] <아난티 소액주주운동, 시작부터 휘청?…주주대표 사익 추구 논란> 관련 (다음뉴스 ─ 언론중재법 피해구제보도)","contents":"아이뉴스24","link":"https://v.daum.net/v/20240426213320825","retrieved":1714089600000},{"title":"[반론보도문] <'부산저축銀' 봐주기 수사' 보도 기자 출연…> 관련 (다음뉴스 ─ 언론중재법 피해구제보도)","contents":"연합뉴스","link":"https://v.daum.net/v/20240426170038062","retrieved":1714089600000},{"title":"[반론보도] <이승기 '50억' 사태 재현되나, 무기한 계약 의혹도···인디 음악 1위 엠피엠지 논란> 기사 관련 (다음뉴스 ─ 언론중재법 피해구제보도)","contents":"서울경제","link":"https://v.daum.net/v/20240426144338429","retrieved":1714089600000},{"title":"조수진 전 더불어민주당 강북을 후보 관련 보도[정정 및 반론보도] (다음뉴스 ─ 언론중재법 피해구제보도)","contents":"경향신문","link":"https://v.daum.net/v/20240424165853158","retrieved":1713916800000},{"title":"[반론보도] 〈'한동훈 비대위' 닻 올리자마자…위원 '과거 발언 논란' 봇물〉 관련 (다음뉴스 ─ 언론중재법 피해구제보도)","contents":"JTBC","link":"https://v.daum.net/v/20240424153441597","retrieved":1713916800000},{"title":"[반론보도] <‘위성정당’ 규탄 민변 임원들, 더불어민주연합 구성참여, 공천도 신청해 논란> 관련 (다음뉴스 ─ 언론중재법 피해구제보도)","contents":"한겨레","link":"https://v.daum.net/v/20240423150507415","retrieved":1713830400000},{"title":"[정정 및 반론]  '한동훈 비서실장' 김형동 의원, 불법 선거운동 정황 잇따라 관련 (다음뉴스 ─ 언론중재법 피해구제보도)","contents":"더팩트","link":"https://v.daum.net/v/20240420192702041","retrieved":1713571200000},{"title":"[반론보도] <친한 학생에게 시험채점·성적입력 맡긴 교사…징계절차 들어가> 관련 (다음뉴스 ─ 언론중재법 피해구제보도)","contents":"한겨레","link":"https://v.daum.net/v/20240418114514043","retrieved":1713398400000},{"title":"[정정보도문] 조수진 전 민주당 후보 관련 보도를 바로잡습니다 (다음뉴스 ─ 언론중재법 피해구제보도)","contents":"서울경제","link":"https://v.daum.net/v/20240415163617190","retrieved":1713139200000},{"title":"[반론보도] 〈'밥퍼' 후원금이 종교시설로?…'억 단위' 사용 정황〉관련 (다음뉴스 ─ 언론중재법 피해구제보도)","contents":"JTBC","link":"https://v.daum.net/v/20240415144837343","retrieved":1713139200000},{"title":"[반론보도] '이재명 방탄 올인…민주당 '종북·급진'과도 손잡았다' 관련 (다음뉴스 ─ 언론중재법 피해구제보도)","contents":"한국경제","link":"https://v.daum.net/v/20240412154010249","retrieved":1712880000000},{"title":"정정보도 <野, 시민사회 몫 비례 후보에 '이재명 캠프' 변호사> 관련 (다음뉴스 ─ 언론중재법 피해구제보도)","contents":"아시아경제","link":"https://v.daum.net/v/20240405145351087","retrieved":1712275200000},{"title":"[반론보도] '셀리버리, 백화점·유흥업소 등서 수억원 '법카' 사용 의혹' 관련 (다음뉴스 ─ 언론중재법 피해구제보도)","contents":"아이뉴스24","link":"https://v.daum.net/v/20240403155427867","retrieved":1712102400000},{"title":"[반론보도] <[단독] 김부겸·정세균, 선대위장 제안 '거절'…유시민 등판설도> 관련 (다음뉴스 ─ 언론중재법 피해구제보도)","contents":"뉴스1","link":"https://v.daum.net/v/20240401161019787","retrieved":1711929600000},{"title":"[반론보도] 「[단독] \"누가 '심해'의 주인입니까\"…시나리오 논란의 전말」 기사 관련 (다음뉴스 ─ 언론중재법 피해구제보도)","contents":"디스패치","link":"https://v.daum.net/v/20240401131600196","retrieved":1711929600000},{"title":"'조국혁신당 비례1번' 박은정 남편, 브이글로벌 코인사기범 공범 변호 논란 (다음뉴스 ─ 불공정기사 모음)","contents":"뉴스1","link":"https://v.daum.net/v/20240329183539328","retrieved":1711670400000},{"title":"[단독] 文때 ‘코인 TF 총괄’ 박은정 남편, 2조원대 코인 사기도 변호 (다음뉴스 ─ 불공정기사 모음)","contents":"조선일보","link":"https://v.daum.net/v/20240329171250957","retrieved":1711670400000},{"title":"공천은 받았는데 '불안불안'...한동훈 비서실장 김형동, 불법 선거운동 고발 잇따라 (다음뉴스 ─ 불공정기사 모음)","contents":"프레시안","link":"https://v.daum.net/v/20240326103237965","retrieved":1711411200000},{"title":"“국회의원 아내가 구의원 법카로 식당 결제” 권익위 신고 (다음뉴스 ─ 불공정기사 모음)","contents":"조선일보","link":"https://v.daum.net/v/20240321205331397","retrieved":1710979200000},{"title":"[단독] \"현직 국회의원 배우자 지역 구의원 법카 유용\" (다음뉴스 ─ 불공정기사 모음)","contents":"매일경제","link":"https://v.daum.net/v/20240321175711678","retrieved":1710979200000},{"title":"\"국민의힘 당원아니다\"... 한동훈 비서실장 김형동 의원, 여론조사 거짓응답 유도 의혹 (다음뉴스 ─ 불공정기사 모음)","contents":"프레시안","link":"https://v.daum.net/v/20240316192406210","retrieved":1710547200000},{"title":"민주당 출신 전 도봉구의장들…\"안귀령 공천이 김근태 정신인가\" (다음뉴스 ─ 불공정기사 모음)","contents":"데일리안","link":"https://v.daum.net/v/20240308054500557","retrieved":1709769600000},{"title":"[단독] 강득구, 4년 전 총선에서 '위장 당원' 모집해 경선 참여 정황 (다음뉴스 ─ 불공정기사 모음)","contents":"오마이뉴스","link":"https://v.daum.net/v/20240307112103752","retrieved":1709769600000},{"title":"[단독] 김부겸·정세균, 선대위장 제안 '거절'…유시민 등판설도 (다음뉴스 ─ 불공정기사 모음)","contents":"뉴스1","link":"https://v.daum.net/v/20240304115245089","retrieved":1709510400000},{"title":"‘김제동 강연 1550만원’ ‘양주, 투기 의혹’…논란 지자체 출신 총선행 (다음뉴스 ─ 불공정기사 모음)","contents":"서울신문","link":"https://v.daum.net/v/20240212140102325","retrieved":1707696000000},{"title":"[데일리안 여론조사] 조전혁이 조희연에 앞서..서울시교육감 가상 양자대결 (다음뉴스 ─ 불공정기사 모음)","contents":"데일리안","link":"https://v.daum.net/v/20220525150004635","retrieved":1653436800000},{"title":"[데일리안 여론조사] 서울시교육감 조희연 선두..'보수후보 3명 합산' 보다는 낮아 (다음뉴스 ─ 불공정기사 모음)","contents":"데일리안","link":"https://v.daum.net/v/20220525150001626","retrieved":1653436800000},{"title":"우승희 '현금 동원' 권리당원 불법 모집 의혹 불거져 (다음뉴스 ─ 불공정기사 모음)","contents":"더팩트","link":"https://v.daum.net/v/20220523194822118","retrieved":1653264000000},{"title":"[단독] 서울 원정 건강검진비 할인 특혜 의혹 이춘희 세종시장 수사 (다음뉴스 ─ 불공정기사 모음)","contents":"시사저널","link":"https://v.daum.net/v/20220420101103421","retrieved":1650412800000},{"title":"[경기교육감 적합도] '보수 단일' 임태희 선두.. 진보 단일화 '변수' (다음뉴스 ─ 불공정기사 모음)","contents":"오마이뉴스","link":"https://v.daum.net/v/20220420061500113","retrieved":1650326400000},{"title":"경기지사 통틀어 김은혜 1위..국힘 내는 유승민 [KSOI] (다음뉴스 ─ 불공정기사 모음)","contents":"서울경제","link":"https://v.daum.net/v/20220418090025234","retrieved":1650240000000},{"title":"이춘희 세종시장 아파트 특공 '시장 찬스' 논란..\"반납해야\" 비난엔 '침묵' (다음뉴스 ─ 불공정기사 모음)","contents":"시사저널","link":"https://v.daum.net/v/20220415155302050","retrieved":1649980800000}]}