{"title":"Combined feed","url":"https://factcheckr.github.io/daumnews/all.xml","elements":[{"title":"인권위 “GOP 투입 전 경계병 교육 의무화” (다음뉴스 ─ 홈)","contents":"정치","link":"https://v.daum.net/v/20230702182906137","retrieved":1688293402285},{"title":"기후변화의 또 다른 위기…‘기후 약자’ (다음뉴스 ─ 홈)","contents":"사회","link":"https://v.daum.net/v/20230702211703443","retrieved":1688301291694},{"title":"두달새 7조원 이탈한 새마을금고, 행안부 메스 든다 (다음뉴스 ─ 홈)","contents":"경제","link":"https://v.daum.net/v/20230702211701441","retrieved":1688301291695},{"title":"갤럭시Z 플립5, 접힌 채로 카톡·사진전송 될 듯 (다음뉴스 ─ 홈)","contents":"경제","link":"https://v.daum.net/v/20230702210306310","retrieved":1688301291702},{"title":"작업장·밭일 온열질환 주의…폭염 시 행동요령은 (다음뉴스 ─ 홈)","contents":"사회","link":"https://v.daum.net/v/20230702211408419","retrieved":1688301291704},{"title":"뼛속까지 시원해지는 기분 [포토] (다음뉴스 ─ 홈)","contents":"문화","link":"https://v.daum.net/v/20230702153413318","retrieved":1688301291705},{"title":"우크라 “러, 자포리자 원자로 4기에 폭발물 설치”···러 원전 ‘고의 파괴’ 계획 거듭 경고 (다음뉴스 ─ 홈)","contents":"국제","link":"https://v.daum.net/v/20230702204859167","retrieved":1688301291711},{"title":"신변 위협 시달리는 전세계 팩트체커들, 그래도 계속 싸우는 이유 (다음뉴스 ─ 홈)","contents":"문화","link":"https://v.daum.net/v/20230702180602827","retrieved":1688289554525},{"title":"까마귀 정전 피해···한전 대구본부에만 일 년에 120억 (다음뉴스 ─ 홈)","contents":"사회","link":"https://v.daum.net/v/20230702203328953","retrieved":1688301291713},{"title":"[단독] 푸틴의 첫 총리가 말하는 바그너 그룹의 비밀 (다음뉴스 ─ 홈)","contents":"국제","link":"https://v.daum.net/v/20230702204811162","retrieved":1688301291714},{"title":"통가 누쿠알로파 북쪽 바다서 규모 6.9 지진 (다음뉴스 ─ 홈)","contents":"국제","link":"https://v.daum.net/v/20230702204554130","retrieved":1688301291726},{"title":"[날씨] 내일 폭염 최대 고비‥다시 장맛비 (다음뉴스 ─ 홈)","contents":"문화","link":"https://v.daum.net/v/20230702204544127","retrieved":1688301291726},{"title":"[와이라노] 도로 위 잔혹사 ‘응급실 뺑뺑이’… 병원은 왜 환자를 거부했나 (다음뉴스 ─ 홈)","contents":"사회","link":"https://v.daum.net/v/20230702205502229","retrieved":1688301291726},{"title":"‘전기요금 폭탄’ 막기... 인천 상가 '안간힘' (다음뉴스 ─ 홈)","contents":"경제","link":"https://v.daum.net/v/20230702160535835","retrieved":1688301291729},{"title":"경기도 여성 공무원 비율 52%… 전국 네번째 높아 (다음뉴스 ─ 홈)","contents":"사회","link":"https://v.daum.net/v/20230702183740249","retrieved":1688293382385},{"title":"경기 국회의원 주최 행사 수백 건인데… 지역 이슈 ‘뒷전’ [집중취재] (다음뉴스 ─ 홈)","contents":"정치","link":"https://v.daum.net/v/20230702204035044","retrieved":1688301291732},{"title":"장마전선 물러나자 찾아온 '폭염'…야외수영장·쇼핑몰에 시민 몰려 (다음뉴스 ─ 홈)","contents":"사회","link":"https://v.daum.net/v/20230702201201558","retrieved":1688301291733},{"title":"윤 대통령, 통일부에 '역할 변화' 촉구... 남북갈등 심화 이어지나 (다음뉴스 ─ 홈)","contents":"정치","link":"https://v.daum.net/v/20230702200012357","retrieved":1688301291735},{"title":"[미리보는 경제] \"4년 뒤, 디지털 유로 나온다\"‥디지털 원은 언제쯤? (다음뉴스 ─ 홈)","contents":"경제","link":"https://v.daum.net/v/20230702203425964","retrieved":1688301291736},{"title":"\"올 수능 교육과정에서 출제\"‥'킬러문항' 없다 거듭 확인 (다음뉴스 ─ 홈)","contents":"사회","link":"https://v.daum.net/v/20230702203424962","retrieved":1688301291738},{"title":"청양 출생 미신고 사건 아동, 현재 7살로 행방 확인 (다음뉴스 ─ 사회 ─ 메인뉴스)","contents":"대전일보","link":"https://v.daum.net/v/20230702201226575","retrieved":1688301301034},{"title":"800만 원에 산 땅 9,450만 원에 되판 중국인…불법 땅 투기 '만연' (다음뉴스 ─ 사회 ─ 메인뉴스)","contents":"MBN","link":"https://v.daum.net/v/20230702195846327","retrieved":1688301301044},{"title":"기후변화의 또 다른 위기…‘기후 약자’ (다음뉴스 ─ 사회 ─ 메인뉴스)","contents":"KBS","link":"https://v.daum.net/v/20230702211703443","retrieved":1688301301045},{"title":"작업장·밭일 온열질환 주의…폭염 시 행동요령은 (다음뉴스 ─ 사회 ─ 메인뉴스)","contents":"KBS","link":"https://v.daum.net/v/20230702211408419","retrieved":1688301301048},{"title":"'킬러문항' 없앤 수능, 11월16일... 누가 수혜자 될까 (다음뉴스 ─ 사회 ─ 메인뉴스)","contents":"오마이뉴스","link":"https://v.daum.net/v/20230702211202397","retrieved":1688301301051},{"title":"최저임금·노란봉투법 혼란 속… 민주노총 3일 총파업 (다음뉴스 ─ 사회 ─ 메인뉴스)","contents":"국민일보","link":"https://v.daum.net/v/20230702203014922","retrieved":1688301301051},{"title":"안정효 선생을 기리며 (다음뉴스 ─ 사회 ─ 메이저)","contents":"조선일보","link":"https://v.daum.net/v/20230702211429423","retrieved":1688301310506},{"title":"“다음 생에도 내 딸로 태어나주렴” 아영이 아빠 눈물의 마지막 편지 (다음뉴스 ─ 사회 ─ 메이저)","contents":"국제신문","link":"https://v.daum.net/v/20230702200357433","retrieved":1688301310511},{"title":"“스쿨존 보행신호만 있었어도 사고 안 났다” (다음뉴스 ─ 사회 ─ 메이저)","contents":"국제신문","link":"https://v.daum.net/v/20230702200354432","retrieved":1688301310517},{"title":"‘살인 더위’에도…일을 멈출 수 없는 사람들 (다음뉴스 ─ 사회 ─ 메이저)","contents":"경향신문","link":"https://v.daum.net/v/20230702205807257","retrieved":1688301310523},{"title":"잠 깨우는 '오토바이 소음' 단속 기준 강화한다…효과는? (다음뉴스 ─ 사회 ─ 메이저)","contents":"SBS","link":"https://v.daum.net/v/20230702205705247","retrieved":1688301310527},{"title":"[와이라노] 도로 위 잔혹사 ‘응급실 뺑뺑이’… 병원은 왜 환자를 거부했나 (다음뉴스 ─ 사회 ─ 메이저)","contents":"국제신문","link":"https://v.daum.net/v/20230702205502229","retrieved":1688301310530},{"title":"부산 스쿨존 교통사고에 교사·시민들 \"통학로 대책 마련하라\" (다음뉴스 ─ 사회 ─ 메이저)","contents":"연합뉴스","link":"https://v.daum.net/v/20230702205219203","retrieved":1688301310533},{"title":"관계성 복잡한 국제 이슈…맥락 짚는 친절한 설명 필요 (다음뉴스 ─ 사회 ─ 메이저)","contents":"한겨레","link":"https://v.daum.net/v/20230702205004177","retrieved":1688301310536},{"title":"대통령 ‘뒷북’ 호통에 놀란 교육부…국립대 사무국장 임용 손뗀다 (다음뉴스 ─ 사회 ─ 메이저)","contents":"한겨레","link":"https://v.daum.net/v/20230702205002176","retrieved":1688301310539},{"title":"'5분 만에'...술집 주인 이어 말리던 손님도 살해 (다음뉴스 ─ 사회 ─ 메이저)","contents":"이데일리","link":"https://v.daum.net/v/20230702204922170","retrieved":1688301310543},{"title":"보호받지 못 하는 아이들…'후견인 선정 단축' 법안 발의 (다음뉴스 ─ 정치 ─ 메인뉴스)","contents":"SBS","link":"https://v.daum.net/v/20230702210015271","retrieved":1688301321293},{"title":"경기 국회의원 주최 행사 수백 건인데… 지역 이슈 ‘뒷전’ [집중취재] (다음뉴스 ─ 정치 ─ 메인뉴스)","contents":"경기일보","link":"https://v.daum.net/v/20230702204035044","retrieved":1688301321295},{"title":"윤 대통령 \"통일부, 대북지원부 아냐\"…\"화해, 협력 부정\" (다음뉴스 ─ 정치 ─ 메인뉴스)","contents":"SBS","link":"https://v.daum.net/v/20230702202405831","retrieved":1688301321297},{"title":"남북대화 대신 대북압박에 주력…통일부 존재 이유 ‘뒤집기’ (다음뉴스 ─ 정치 ─ 메인뉴스)","contents":"한겨레","link":"https://v.daum.net/v/20230702202010756","retrieved":1688301321305},{"title":"'2차 공공기관 지방이전' 늦어진다…'혁신도시 시즌2' 희망고문 장기화 (다음뉴스 ─ 정치 ─ 메인뉴스)","contents":"대전일보","link":"https://v.daum.net/v/20230702201423661","retrieved":1688301321306},{"title":"尹 '역할 변화' 주문에…통일부, 대화서 북한 인권 중시로 (다음뉴스 ─ 정치 ─ 메인뉴스)","contents":"뉴시스","link":"https://v.daum.net/v/20230702200236393","retrieved":1688301321306},{"title":"윤 대통령, 통일부에 '역할 변화' 촉구... 남북갈등 심화 이어지나 (다음뉴스 ─ 정치 ─ 메이저)","contents":"한국일보","link":"https://v.daum.net/v/20230702200012357","retrieved":1688301331942},{"title":"장관들 복귀 앞둔 與…'지역구 쟁탈전' 조짐 (다음뉴스 ─ 정치 ─ 메이저)","contents":"한국경제","link":"https://v.daum.net/v/20230702184201312","retrieved":1688301331948},{"title":"\"김기현 사과 없으면 상응 조치\" vs \"할 말 했다\" (다음뉴스 ─ 정치 ─ 메이저)","contents":"YTN","link":"https://v.daum.net/v/20230702191614711","retrieved":1688293354366},{"title":"'먹튀 논란' 언론에 직접 해명한 김기현 아들 (다음뉴스 ─ 정치 ─ 메이저)","contents":"한국경제","link":"https://v.daum.net/v/20230702184004289","retrieved":1688301331950},{"title":"[단독]‘용산 5차관’ 기강 잡기 착수…“정책에 이념 섞지 말라” (다음뉴스 ─ 정치 ─ 메이저)","contents":"채널A","link":"https://v.daum.net/v/20230702191158651","retrieved":1688293354370},{"title":"국방부, 예비군 참가자 불이익 받아도 보호는 ‘전무’ (다음뉴스 ─ 정치 ─ 메이저)","contents":"세계일보","link":"https://v.daum.net/v/20230702190132530","retrieved":1688293392276},{"title":"민주 혁신위 '꼼수 탈당' 정조준... '불체포특권 포기 서약'은 답보 (다음뉴스 ─ 정치 ─ 메이저)","contents":"한국일보","link":"https://v.daum.net/v/20230702190051518","retrieved":1688293392278},{"title":"올해 법안소위 10번 중 1번, 의원 절반이상 자리비워 (다음뉴스 ─ 정치 ─ 메이저)","contents":"동아일보","link":"https://v.daum.net/v/20230702180251796","retrieved":1688289507425},{"title":"입법 폭주하던 巨野…방송법은 '속도조절' 나선 이유 (다음뉴스 ─ 정치 ─ 메이저)","contents":"한국경제","link":"https://v.daum.net/v/20230702184103307","retrieved":1688293402282},{"title":"미중 경쟁심화 속 韓中日 협력 전망은…내일 칭다오서 3국 포럼 (다음뉴스 ─ 정치 ─ 메이저)","contents":"연합뉴스","link":"https://v.daum.net/v/20230702183510211","retrieved":1688293392279},{"title":"두달새 7조원 이탈한 새마을금고, 행안부 메스 든다 (다음뉴스 ─ 경제 ─ 메인뉴스)","contents":"쿠키뉴스","link":"https://v.daum.net/v/20230702211701441","retrieved":1688301343063},{"title":"폭염 속 “밭일도 쉬어가요”…도심은 ‘이글이글’ (다음뉴스 ─ 경제 ─ 메인뉴스)","contents":"KBS","link":"https://v.daum.net/v/20230702210929372","retrieved":1688301343063},{"title":"정치인 출신 한전사장 나올까… 김동철 유력 관측 (다음뉴스 ─ 경제 ─ 메인뉴스)","contents":"세계일보","link":"https://v.daum.net/v/20230702210146283","retrieved":1688301343067},{"title":"무역수지 16개월 만에 ‘흑자’ 반전…‘불황형’ 우려도 (다음뉴스 ─ 경제 ─ 메인뉴스)","contents":"경향신문","link":"https://v.daum.net/v/20230702205828258","retrieved":1688301343069},{"title":"中 증설 러시에…롯데케미칼·GS칼텍스도 '고부가'에 집중 (다음뉴스 ─ 경제 ─ 메인뉴스)","contents":"한국경제","link":"https://v.daum.net/v/20230702183905277","retrieved":1688301343071},{"title":"한국인 취향 맞춰… 차 덩치 갈수록 ‘벌크업’ (다음뉴스 ─ 경제 ─ 메인뉴스)","contents":"세계일보","link":"https://v.daum.net/v/20230702204857166","retrieved":1688301343071},{"title":"초역세권 3천 세대 아파트 공사비 갈등…공급난 불씨 되나 (다음뉴스 ─ 경제 ─ 메이저)","contents":"SBS","link":"https://v.daum.net/v/20230702203604982","retrieved":1688301352071},{"title":"[미리보는 경제] \"4년 뒤, 디지털 유로 나온다\"‥디지털 원은 언제쯤? (다음뉴스 ─ 경제 ─ 메이저)","contents":"MBC","link":"https://v.daum.net/v/20230702203425964","retrieved":1688301352072},{"title":"하늘을 나는 차 UAM 상용화 코앞‥한국은? (다음뉴스 ─ 경제 ─ 메이저)","contents":"MBC","link":"https://v.daum.net/v/20230702202214799","retrieved":1688301352073},{"title":"대전예당, 재활용 안 되는 의상비 매년 1억 5000만 원…낭비 논란 (다음뉴스 ─ 경제 ─ 메이저)","contents":"대전일보","link":"https://v.daum.net/v/20230702201441677","retrieved":1688301352075},{"title":"반등 조짐 보인 상반기 대전 부동산 시장…하반기 전망은? (다음뉴스 ─ 경제 ─ 메이저)","contents":"대전일보","link":"https://v.daum.net/v/20230702201430668","retrieved":1688301352075},{"title":"10곳 중 1곳 이상 빈 점포…엔데믹에도 대전 상가 공실률 증가 (다음뉴스 ─ 경제 ─ 메이저)","contents":"대전일보","link":"https://v.daum.net/v/20230702201428666","retrieved":1688301352076},{"title":"새마을금고 예금 두 달간 7조 이탈 (다음뉴스 ─ 경제 ─ 메이저)","contents":"세계일보","link":"https://v.daum.net/v/20230702200120376","retrieved":1688301352080},{"title":"훈풍 부는 아파트 분양권 시장 [김경민의 부동산NOW] (다음뉴스 ─ 경제 ─ 메이저)","contents":"매경이코노미","link":"https://v.daum.net/v/20230702195117219","retrieved":1688301352080},{"title":"소는 헐값에 팔리는데…사먹을 땐 제값 (다음뉴스 ─ 경제 ─ 메이저)","contents":"채널A","link":"https://v.daum.net/v/20230702193554971","retrieved":1688301352080},{"title":"채권·공모주 동시투자…하반기 '대어급' 상장땐 초과수익 [이런 펀드 어때요?] (다음뉴스 ─ 경제 ─ 메이저)","contents":"파이낸셜뉴스","link":"https://v.daum.net/v/20230702191526705","retrieved":1688293410640},{"title":"“한국 사교육비, 아이슬란드 GDP랑 맞먹어”… CNN도 ‘Hagwon’ 조명 (다음뉴스 ─ 국제 ─ 메인뉴스)","contents":"조선일보","link":"https://v.daum.net/v/20230702212624543","retrieved":1688301361064},{"title":"신변 위협 시달리는 전세계 팩트체커들, 그래도 계속 싸우는 이유 (다음뉴스 ─ 국제 ─ 메인뉴스)","contents":"오마이뉴스","link":"https://v.daum.net/v/20230702180602827","retrieved":1688289554525},{"title":"우크라 “러, 자포리자 원자로 4기에 폭발물 설치”···러 원전 ‘고의 파괴’ 계획 거듭 경고 (다음뉴스 ─ 국제 ─ 메인뉴스)","contents":"경향신문","link":"https://v.daum.net/v/20230702204859167","retrieved":1688301361066},{"title":"[단독] 푸틴의 첫 총리가 말하는 바그너 그룹의 비밀 (다음뉴스 ─ 국제 ─ 메인뉴스)","contents":"SBS","link":"https://v.daum.net/v/20230702204811162","retrieved":1688301361066},{"title":"'욱일 문양 보드' 11살 참교육? 그 개운치 않은 뒷맛 (다음뉴스 ─ 국제 ─ 메인뉴스)","contents":"오마이뉴스","link":"https://v.daum.net/v/20230702203943032","retrieved":1688301361067},{"title":"미국도 일본도 되는데 한국만 '안 돼'…그사이 중국 속내 (다음뉴스 ─ 국제 ─ 메인뉴스)","contents":"SBS","link":"https://v.daum.net/v/20230702203907020","retrieved":1688301361069},{"title":"'우향우 판결' 쏟아낸 미국 연방대법원... 보혁 논쟁 한복판에 서다 (다음뉴스 ─ 국제 ─ 메이저)","contents":"한국일보","link":"https://v.daum.net/v/20230702203008921","retrieved":1688301371859},{"title":"중국 관광객 '벽돌' 피습‥프랑스 시위 \"폭동 수준, 여행객 안전 유의\" (다음뉴스 ─ 국제 ─ 메이저)","contents":"MBC","link":"https://v.daum.net/v/20230702201614704","retrieved":1688301371861},{"title":"적진 침투하다가 ‘번쩍’… 러軍 최종병기 자폭탱크 봤더니 (다음뉴스 ─ 국제 ─ 메이저)","contents":"조선일보","link":"https://v.daum.net/v/20230702200304407","retrieved":1688301371862},{"title":"\"환경 지키는 보람에 1,776계단 올랐죠\"…캐나다 한인 운전기사의 기부 도전 (다음뉴스 ─ 국제 ─ 메이저)","contents":"YTN","link":"https://v.daum.net/v/20230702195624292","retrieved":1688301371865},{"title":"5m 탁자 앉던 푸틴이 변했다…반란 후 보인 '기이한 광경' 깜짝 (다음뉴스 ─ 국제 ─ 메이저)","contents":"중앙일보","link":"https://v.daum.net/v/20230702194742164","retrieved":1688301371869},{"title":"도쿄서 \"강제동원 희생자 추도비 철거 반대\" 집회… 우익의 방해 예고에 한때 긴장감 (다음뉴스 ─ 국제 ─ 메이저)","contents":"한국일보","link":"https://v.daum.net/v/20230702194511127","retrieved":1688301371870},{"title":"日 \"한국에 규제 철폐 요구\"...日 어민, 여전히 방류 반대 (다음뉴스 ─ 국제 ─ 메이저)","contents":"YTN","link":"https://v.daum.net/v/20230702191624714","retrieved":1688293429587},{"title":"“집에서 불고기-고추장 치킨 만들어요” 파리 가정집 주방 파고든 K푸드 (다음뉴스 ─ 국제 ─ 메이저)","contents":"동아일보","link":"https://v.daum.net/v/20230702185802480","retrieved":1688293354375},{"title":"\"진짜 붙는다\"는 머스크와 저커버그, 숨겨진 이유는? (다음뉴스 ─ 국제 ─ 메이저)","contents":"노컷뉴스","link":"https://v.daum.net/v/20230702185401437","retrieved":1688293429596},{"title":"\"게이와 싸울 자, 트럼프 아닌 나\"... 디샌티스 독한 입에 보수단체마저 \"선 넘었다\" (다음뉴스 ─ 국제 ─ 메이저)","contents":"한국일보","link":"https://v.daum.net/v/20230702184547344","retrieved":1688293429599},{"title":"기미·주근깨 심해지는 여름철 관리법은 (다음뉴스 ─ 문화 ─ 메인뉴스)","contents":"비즈워치","link":"https://v.daum.net/v/20230702110002864","retrieved":1688301381600},{"title":"‘쭈글쭈글’ 사과 냉해 피해 막는 삼총사[1.5도 너머 기후위기적응을 말하다] (다음뉴스 ─ 문화 ─ 메인뉴스)","contents":"경향신문","link":"https://v.daum.net/v/20230702212920560","retrieved":1688301381602},{"title":"[부산갈매기] 무력감이 나를 덮칠 때, 이 생각은 도움이 됩니다 (다음뉴스 ─ 문화 ─ 메인뉴스)","contents":"오마이뉴스","link":"https://v.daum.net/v/20230702203901016","retrieved":1688301381604},{"title":"[날씨] 내일 폭염 최대 고비‥다시 장맛비 (다음뉴스 ─ 문화 ─ 메인뉴스)","contents":"MBC","link":"https://v.daum.net/v/20230702204544127","retrieved":1688301381606},{"title":"도둑 맞고 팔려 가고... 고려 주전자의 기구한 사연 (다음뉴스 ─ 문화 ─ 메인뉴스)","contents":"오마이뉴스","link":"https://v.daum.net/v/20230702204201065","retrieved":1688301381608},{"title":"술 마신 뒤 감기약?...무심코 여겼다간 큰일 (다음뉴스 ─ 문화 ─ 메인뉴스)","contents":"코메디닷컴","link":"https://v.daum.net/v/20230702192314810","retrieved":1688301381610},{"title":"[알고보면]'인디아나 존스' 배경이 1930년대인 이유(中) (다음뉴스 ─ 문화 ─ 메이저)","contents":"아시아경제","link":"https://v.daum.net/v/20230702191952773","retrieved":1688293448216},{"title":"사람 닮은 로봇 '에버6', 국립극장서 지휘자로 데뷔하다 (다음뉴스 ─ 문화 ─ 메이저)","contents":"이데일리","link":"https://v.daum.net/v/20230702190027511","retrieved":1688293448218},{"title":"허리·목통증에 '아편성진통제'...효과 떨어진다? (다음뉴스 ─ 문화 ─ 메이저)","contents":"코메디닷컴","link":"https://v.daum.net/v/20230702181056900","retrieved":1688293354382},{"title":"\"사람은 다 조금씩 이상... 튀어도 괜찮아요\" (다음뉴스 ─ 문화 ─ 메이저)","contents":"오마이뉴스","link":"https://v.daum.net/v/20230702142703129","retrieved":1688293354397},{"title":"‘두 아이 논란’ 도연 스님, 명상 유료강좌 열어…자숙은 뒷전? (다음뉴스 ─ 문화 ─ 메이저)","contents":"문화일보","link":"https://v.daum.net/v/20230702185106406","retrieved":1688293448225},{"title":"신변 위협 시달리는 전세계 팩트체커들, 그래도 계속 싸우는 이유 (다음뉴스 ─ 문화 ─ 메이저)","contents":"오마이뉴스","link":"https://v.daum.net/v/20230702180602827","retrieved":1688289554525},{"title":"여성 50%가 심한 생리통·증후군 경험하지만, 대처법은… (다음뉴스 ─ 문화 ─ 메이저)","contents":"헬스조선","link":"https://v.daum.net/v/20230702180015731","retrieved":1688289482545},{"title":"믿음과 의심 사이···나무 위에선 아직 '전쟁 중' (다음뉴스 ─ 문화 ─ 메이저)","contents":"서울경제","link":"https://v.daum.net/v/20230702174849509","retrieved":1688289554527},{"title":"AI·양자컴·C테크 … 첨단기술 향하는 곳에 '인류의 길' 있다 (다음뉴스 ─ 문화 ─ 메이저)","contents":"매일경제","link":"https://v.daum.net/v/20230702171801950","retrieved":1688286347485},{"title":"밤새워 앉아서 게임만 하는 청소년들 … 어른 되면 '염증' 시달릴수도 (다음뉴스 ─ 문화 ─ 메이저)","contents":"매일경제","link":"https://v.daum.net/v/20230702163311259","retrieved":1688286357006},{"title":"“삼성 쓸데없이 왜 접어” 역대급 삼성 제품 조롱하는 아이폰 (다음뉴스 ─ IT ─ 메인뉴스)","contents":"헤럴드경제","link":"https://v.daum.net/v/20230702195147229","retrieved":1688301403899},{"title":"전기차 충전도 로봇이 한다 (다음뉴스 ─ IT ─ 메인뉴스)","contents":"비즈워치","link":"https://v.daum.net/v/20230702180003710","retrieved":1688301403909},{"title":"尹 약속 현실로…전 세계 '韓 과학계 스타' 한자리에 (다음뉴스 ─ IT ─ 메인뉴스)","contents":"이데일리","link":"https://v.daum.net/v/20230702120052988","retrieved":1688293466938},{"title":"'잊힐 권리' 요청 가장 많았던 사이트는...유튜브 페이스북 네이버 (다음뉴스 ─ IT ─ 메인뉴스)","contents":"국제신문","link":"https://v.daum.net/v/20230702185736474","retrieved":1688293354377},{"title":"뉴스 알고리즘은 '정치적 쟁점'이 아니다 (다음뉴스 ─ IT ─ 메인뉴스)","contents":"지디넷코리아","link":"https://v.daum.net/v/20230702181809989","retrieved":1688293466940},{"title":"40년 만의 나스닥 랠리…애플 시총 3조弗 '한국 GDP의 1.7배' (다음뉴스 ─ IT ─ 메인뉴스)","contents":"한국경제","link":"https://v.daum.net/v/20230702181607968","retrieved":1688293466942},{"title":"'지구와 쌍둥이 행성' 금성, 대기 미스터리 푸는 '특급 작전' 개시 (다음뉴스 ─ IT ─ 메이저)","contents":"머니투데이","link":"https://v.daum.net/v/20230702181427943","retrieved":1688289571016},{"title":"'넥스트 트위터' 둘러싼 혈투 [정혜진의 Whynot 실리콘밸리] (다음뉴스 ─ IT ─ 메이저)","contents":"서울경제","link":"https://v.daum.net/v/20230702180638833","retrieved":1688289571016},{"title":"“얘는 배달비 단돈 1천원!” 무법 배달 오토바이 이제 그만 (다음뉴스 ─ IT ─ 메이저)","contents":"헤럴드경제","link":"https://v.daum.net/v/20230702175107551","retrieved":1688289482513},{"title":"거침없는 ‘애플 제국’… 사상 최초 시총 3조 달러 돌파, 한국GDP 1.7배 (다음뉴스 ─ IT ─ 메이저)","contents":"국민일보","link":"https://v.daum.net/v/20230702172114004","retrieved":1688286364292},{"title":"글로벌 반도체社, 한국서 인재확보 전쟁 (다음뉴스 ─ IT ─ 메이저)","contents":"매일경제","link":"https://v.daum.net/v/20230702171514897","retrieved":1688286364295},{"title":"“AI 모르면 도태”… 산업계, 임직원 ‘AI 역량’ 키우기 봇물 (다음뉴스 ─ IT ─ 메이저)","contents":"국민일보","link":"https://v.daum.net/v/20230702170603739","retrieved":1688286267916},{"title":"“강렬한 핫핑크, 예쁜가요?” 핑크에 꽂힌 아이폰 ‘이렇게’ 나온다? (다음뉴스 ─ IT ─ 메이저)","contents":"헤럴드경제","link":"https://v.daum.net/v/20230702165101502","retrieved":1688286267917},{"title":"[뉴스줌인]“대형 공공SW사업 기준 불명확”…‘中企 상생’도 의견 갈려 (다음뉴스 ─ IT ─ 메이저)","contents":"전자신문","link":"https://v.daum.net/v/20230702170105680","retrieved":1688286364300},{"title":"위기인가 기회인가, 챗GPT 시대 부산의 미래를 말하다 (다음뉴스 ─ IT ─ 메이저)","contents":"국제신문","link":"https://v.daum.net/v/20230702165734612","retrieved":1688286364300},{"title":"삼성-LG ‘중국 딜레마’...시장은 크지만 매출 계속 하락 (다음뉴스 ─ IT ─ 메이저)","contents":"전자신문","link":"https://v.daum.net/v/20230702160131773","retrieved":1688282270860},{"title":"대전 교차로서 승용차 가로등 받아… 60대 운전자 부상 (다음뉴스 ─ 포토)","contents":"교통사고","link":"https://gallery.v.daum.net/p/viewer/1473/0iLRPEsb47","retrieved":1688301425780},{"title":"“현장실습생 근로계약서·최저임금 보장하라”[포토뉴스] (다음뉴스 ─ 포토)","contents":"포토뉴스","link":"https://gallery.v.daum.net/p/viewer/377110/BTak9gcpSb","retrieved":1688301425783},{"title":"쪽방촌 ‘쿨링포그’ 더위 식혀줄까[포토뉴스] (다음뉴스 ─ 포토)","contents":"무더운 한반도","link":"https://gallery.v.daum.net/p/viewer/111971/H33mriatlT","retrieved":1688301425785},{"title":"우주 망원경 ‘유클리드’ 발사 모습 촬영하는 관광객 (다음뉴스 ─ 포토)","contents":"스페이스X","link":"https://gallery.v.daum.net/p/viewer/1616/51tN40zcpn","retrieved":1688301425787},{"title":"인명 구조 나서는 경포해변 드론 (다음뉴스 ─ 포토)","contents":"강원도 풍경","link":"https://gallery.v.daum.net/p/viewer/5035853/QM49ebfOM0","retrieved":1688301425789},{"title":"‘체감온도 35도’... 물놀이 즐기는 아이들  [서울포토] (다음뉴스 ─ 포토)","contents":"서울포토","link":"https://gallery.v.daum.net/p/viewer/674200/PdL77Y5JT0","retrieved":1688293483281},{"title":"인종차별에 들끓는 佛···닷새째 격렬 시위 (다음뉴스 ─ 포토)","contents":"프랑스 마크롱 대통령","link":"https://gallery.v.daum.net/p/viewer/2904/Wu4bi26hvn","retrieved":1688289587872},{"title":"‘장마 주춤·폭염 기승’…전국 해수욕장 전면 개장[정동길 옆 사진관] (다음뉴스 ─ 포토)","contents":"정동길 옆 사진관","link":"https://gallery.v.daum.net/p/viewer/661278/pHMemRnXvH","retrieved":1688286379312},{"title":"무더위 피해 계곡 찾은 시민들 (다음뉴스 ─ 포토)","contents":"오늘의 한국 풍경","link":"https://gallery.v.daum.net/p/viewer/1783949/FglwyNEuNq","retrieved":1688282286995},{"title":"김연경 은퇴와 와르르 무너진 대한민국 여자배구 (다음뉴스 ─ 포토)","contents":"도로 위에 와르르","link":"https://gallery.v.daum.net/p/viewer/346997/qdnKc8MTu5","retrieved":1688282286997},{"title":"물놀이 즐기며 '폭염 탈출' [TF사진관] (다음뉴스 ─ 포토)","contents":"TF사진관","link":"https://gallery.v.daum.net/p/viewer/5024184/88gkDQdYzV","retrieved":1688282286999},{"title":"피서 즐기는 참새 (다음뉴스 ─ 포토)","contents":"서울의 풍경","link":"https://gallery.v.daum.net/p/viewer/1461/XE3vbWZdbP","retrieved":1688279058620},{"title":"부산 7개 해수욕장 전면 개장 (다음뉴스 ─ 포토)","contents":"부산은 지금","link":"https://gallery.v.daum.net/p/viewer/5035065/VWsXXEsbKq","retrieved":1688279058621},{"title":"휘발유 9주·경유 10주째 판매가격 하락 (다음뉴스 ─ 포토)","contents":"기름값 현황","link":"https://gallery.v.daum.net/p/viewer/5035080/UUIgGcrqUu","retrieved":1688275161154},{"title":"청계천에 뱀 머리 닮은 물고기 출몰[청계천 옆 사진관] (다음뉴스 ─ 포토)","contents":"청계천 옆 사진관","link":"https://gallery.v.daum.net/p/viewer/344179/3Ct62Htnmk","retrieved":1688275161154},{"title":"주권 반환 행사서 건배하는 존 리 홍콩 행정장관 (다음뉴스 ─ 포토)","contents":"홍콩은 지금","link":"https://gallery.v.daum.net/p/viewer/5030473/878qH0zc7J","retrieved":1688271815362},{"title":"'캐나다로 출국' KDRT, 산불 진화 지원 나선다 [쿠키포토] (다음뉴스 ─ 포토)","contents":"쿠키포토","link":"https://gallery.v.daum.net/p/viewer/5620091/bOWufRnXp8","retrieved":1688267210466},{"title":"\"더위야 가라\" (다음뉴스 ─ 포토)","contents":"미국은 지금","link":"https://gallery.v.daum.net/p/viewer/1476/xArUECT6Kh","retrieved":1688263110894},{"title":"'30년 국수 대접' 대전 구암사 나눔회·북천 스님 (다음뉴스 ─ 포토)","contents":"훈훈한 미담","link":"https://gallery.v.daum.net/p/viewer/1504/uidM3BVs01","retrieved":1688263110895},{"title":"캐나다 산불 진화 대한민국 해외긴급구호대, 화이팅 (다음뉴스 ─ 포토)","contents":"인천공항 풍경","link":"https://gallery.v.daum.net/p/viewer/31583/PG2KaEsb9P","retrieved":1688263110897},{"title":"[영화 감독 김기덕 미투 사건 관련 정정보도문] (다음뉴스 ─ 언론사 고침기사)","contents":"노컷뉴스","link":"https://v.daum.net/v/20230630235700613","retrieved":1688083200000},{"title":"[영화감독 김기덕 미투 사건 관련 정정보도문] (다음뉴스 ─ 언론사 고침기사)","contents":"KBS","link":"https://v.daum.net/v/20230630170010955","retrieved":1688083200000},{"title":"[바로잡습니다] 27일 자 A8면 ‘막말 없이 아름다운 언어로 정치… JP의 삶 돌아보면 마음이 찔려’ 기사에서 (다음뉴스 ─ 언론사 고침기사)","contents":"조선일보","link":"https://v.daum.net/v/20230630030640591","retrieved":1687996800000},{"title":"[정정 및 반론보도]'공직으로 간 아가동산 변호사들' 관련 (다음뉴스 ─ 언론사 고침기사)","contents":"중앙일보","link":"https://v.daum.net/v/20230624235530714","retrieved":1687564800000},{"title":"[정정보도]<'차명투자' 존 리에 직무정지 중징계 처분> 관련 (다음뉴스 ─ 언론사 고침기사)","contents":"아시아경제","link":"https://v.daum.net/v/20230622170024023","retrieved":1687392000000},{"title":"[정정보도] ＜업비트 \"김남국, 자금세탁 매우 의심되는 비정상적 거래\"＞관련 (다음뉴스 ─ 언론사 고침기사)","contents":"YTN","link":"https://v.daum.net/v/20230621150302320","retrieved":1687305600000},{"title":"[정정보도] <업비트 “김남국, 코인 비정상 거래... 자금세탁 의심”> 관련 (다음뉴스 ─ 언론사 고침기사)","contents":"한경비즈니스","link":"https://v.daum.net/v/20230621133702817","retrieved":1687305600000},{"title":"[정정보도문] 영화감독 김기덕 미투 사건 관련 보도를 바로잡습니다 (다음뉴스 ─ 언론사 고침기사)","contents":"아시아경제","link":"https://v.daum.net/v/20230621080242844","retrieved":1687219200000},{"title":"[정정보도]금감원의 존리 전 대표에 대한 중징계 처분 관련 (다음뉴스 ─ 언론사 고침기사)","contents":"노컷뉴스","link":"https://v.daum.net/v/20230620160003320","retrieved":1687219200000},{"title":"[정정보도] ‘금감원, 존리 전 메리츠자산운용 대표 직무정지 중징계 처분’ 관련 (다음뉴스 ─ 언론사 고침기사)","contents":"세계일보","link":"https://v.daum.net/v/20230620144325077","retrieved":1687219200000},{"title":"[정정보도] 존 리 전 메리츠자산운용 대표 금감원 중징계 보도 관련 (다음뉴스 ─ 언론사 고침기사)","contents":"뉴스1","link":"https://v.daum.net/v/20230617081110835","retrieved":1686873600000},{"title":"[정정·반론보도]<'청렴도 하위' 경찰청, 3년간 비위 적발 징계처분 1390명> 관련 (다음뉴스 ─ 언론사 고침기사)","contents":"오마이뉴스","link":"https://v.daum.net/v/20230616172705763","retrieved":1686873600000},{"title":"[정정보도]존 리 전 메리츠자산운용 대표 중징계 보도 관련 (다음뉴스 ─ 언론사 고침기사)","contents":"파이낸셜뉴스","link":"https://v.daum.net/v/20230616153609664","retrieved":1686873600000},{"title":"[정정보도]존 리 전 메리츠자산운용 대표 중징계 보도 관련 (다음뉴스 ─ 언론사 고침기사)","contents":"머니투데이","link":"https://v.daum.net/v/20230616114811932","retrieved":1686873600000},{"title":"[바로잡습니다] “심정지 민노총 집회자 생명 구한 女기동대원들” 관련 (다음뉴스 ─ 언론사 고침기사)","contents":"동아일보","link":"https://v.daum.net/v/20230616030449783","retrieved":1686787200000},{"title":"[정정보도] 존 리 전 메리츠자산운용 대표 중징계 관련 (다음뉴스 ─ 언론사 고침기사)","contents":"헤럴드경제","link":"https://v.daum.net/v/20230615160408165","retrieved":1686787200000},{"title":"[정정보도] '개미 멘토' 존리의 추락…금감원, 직무정지·과징금 등 중징계 기사 관련 (다음뉴스 ─ 언론사 고침기사)","contents":"아이뉴스24","link":"https://v.daum.net/v/20230615135821808","retrieved":1686787200000},{"title":"[알립니다] 존리 전 대표 중징계 처분 관련 (다음뉴스 ─ 언론중재법 피해구제보도)","contents":"서울경제","link":"https://v.daum.net/v/20230626210028224","retrieved":1687737600000},{"title":"[알려왔습니다] 강릉당 \"원조 주장 권리 누구에게도 없어...독자 레시피와 디자인\" (다음뉴스 ─ 언론중재법 피해구제보도)","contents":"MBN","link":"https://v.daum.net/v/20230626110039749","retrieved":1687737600000},{"title":"[정정 및 반론보도]'공직으로 간 아가동산 변호사들' 관련 (다음뉴스 ─ 언론중재법 피해구제보도)","contents":"중앙일보","link":"https://v.daum.net/v/20230624235530714","retrieved":1687564800000},{"title":"[알립니다]<국민의힘 “업비트 측, 김남국 거래 자금세탁 의심 언급”> 관련 (다음뉴스 ─ 언론중재법 피해구제보도)","contents":"채널A","link":"https://v.daum.net/v/20230623224042208","retrieved":1687478400000},{"title":"[정정보도] 금감원의 존리 전 대표에 대한 중징계 처분 관련 (다음뉴스 ─ 언론중재법 피해구제보도)","contents":"YTN","link":"https://v.daum.net/v/20230621152702398","retrieved":1687305600000},{"title":"[정정보도] <업비트 “김남국, 코인 비정상 거래... 자금세탁 의심”> 관련 (다음뉴스 ─ 언론중재법 피해구제보도)","contents":"한경비즈니스","link":"https://v.daum.net/v/20230621133702817","retrieved":1687305600000},{"title":"[정정보도]금감원의 존리 전 대표에 대한 중징계 처분 관련 (다음뉴스 ─ 언론중재법 피해구제보도)","contents":"노컷뉴스","link":"https://v.daum.net/v/20230620160003320","retrieved":1687219200000},{"title":"[반론보도] <'고성으로 얼룩진 김태흠 충남지사-태안군민' 대화> 관련 (다음뉴스 ─ 언론중재법 피해구제보도)","contents":"오마이뉴스","link":"https://v.daum.net/v/20230619094501381","retrieved":1687132800000},{"title":"[정정·반론보도]<'청렴도 하위' 경찰청, 3년간 비위 적발 징계처분 1390명> 관련 (다음뉴스 ─ 언론중재법 피해구제보도)","contents":"오마이뉴스","link":"https://v.daum.net/v/20230616172705763","retrieved":1686873600000},{"title":"[반론] 완주군 공공승마장 위탁운영업체 선정 관련 (다음뉴스 ─ 언론중재법 피해구제보도)","contents":"쿠키뉴스","link":"https://v.daum.net/v/20230614100058356","retrieved":1686700800000},{"title":"[반론보도] 〈이정근노트 “친문자금책” 홈앤쇼핑, 1000억원대 비자금 의혹〉 관련 (다음뉴스 ─ 언론중재법 피해구제보도)","contents":"시사저널","link":"https://v.daum.net/v/20230613180404771","retrieved":1686614400000},{"title":"[반론보도] 「“김기문 중소기업중앙회장, 중소기업 대출 알선 등 처리”」 관련 (다음뉴스 ─ 언론중재법 피해구제보도)","contents":"시사저널","link":"https://v.daum.net/v/20230613180402770","retrieved":1686614400000},{"title":"[반론보도] 〈이정근노트 “김기문중소기업중앙회장, 중소기업대출알선 등 처리”〉 관련 (다음뉴스 ─ 언론중재법 피해구제보도)","contents":"시사저널","link":"https://v.daum.net/v/20230613180358766","retrieved":1686614400000},{"title":"[바로잡습니다] “[단독]“나라 넘어갈 뻔했다”… 檢 ‘간첩단’ 수사팀 11명으로 증원” 관련 (다음뉴스 ─ 언론중재법 피해구제보도)","contents":"동아일보","link":"https://v.daum.net/v/20230607164710619","retrieved":1686096000000},{"title":"[반론보도]'견미리家' 투자했던 '보타바이오' 주가의 타임라인 기사 관련 (다음뉴스 ─ 언론중재법 피해구제보도)","contents":"뉴스1","link":"https://v.daum.net/v/20230530103428116","retrieved":1685404800000},{"title":"[반론보도]<근로시간제 개편안 '상한캡' 없앤다> 관련 (다음뉴스 ─ 언론중재법 피해구제보도)","contents":"머니투데이","link":"https://v.daum.net/v/20230526154002896","retrieved":1685059200000},{"title":"[반론보도] GTX-C 도봉구간 '지하화' 확정…野 지역의원들 '지상화 가능성' 정말 몰랐을까 관련 (다음뉴스 ─ 언론중재법 피해구제보도)","contents":"더팩트","link":"https://v.daum.net/v/20230524103625014","retrieved":1684886400000},{"title":"[데일리안 여론조사] 조전혁이 조희연에 앞서..서울시교육감 가상 양자대결 (다음뉴스 ─ 불공정기사 모음)","contents":"데일리안","link":"https://v.daum.net/v/20220525150004635","retrieved":1653436800000},{"title":"[데일리안 여론조사] 서울시교육감 조희연 선두..'보수후보 3명 합산' 보다는 낮아 (다음뉴스 ─ 불공정기사 모음)","contents":"데일리안","link":"https://v.daum.net/v/20220525150001626","retrieved":1653436800000},{"title":"우승희 '현금 동원' 권리당원 불법 모집 의혹 불거져 (다음뉴스 ─ 불공정기사 모음)","contents":"더팩트","link":"https://v.daum.net/v/20220523194822118","retrieved":1653264000000},{"title":"[현장에서] 삭발·정당색깔 점퍼..'교육' 실종된 교육감 유세 현장 (다음뉴스 ─ 불공정기사 모음)","contents":"중앙일보","link":"https://v.daum.net/v/20220520000259007","retrieved":1652918400000},{"title":"[단독] 서울 원정 건강검진비 할인 특혜 의혹 이춘희 세종시장 수사 (다음뉴스 ─ 불공정기사 모음)","contents":"시사저널","link":"https://v.daum.net/v/20220420101103421","retrieved":1650412800000},{"title":"경기지사 통틀어 김은혜 1위..국힘 내는 유승민 [KSOI] (다음뉴스 ─ 불공정기사 모음)","contents":"서울경제","link":"https://v.daum.net/v/20220418090025234","retrieved":1650240000000},{"title":"이춘희 세종시장 아파트 특공 '시장 찬스' 논란..\"반납해야\" 비난엔 '침묵' (다음뉴스 ─ 불공정기사 모음)","contents":"시사저널","link":"https://v.daum.net/v/20220415155302050","retrieved":1649980800000},{"title":"[단독] 이춘희 세종시장 재산 신고 '특공' 아파트 취득 논란일 듯 (다음뉴스 ─ 불공정기사 모음)","contents":"시사저널","link":"https://v.daum.net/v/20220412144002683","retrieved":1649721600000},{"title":"민주당 기장군수 후보 적합도 조사서 우성빈 군의원 우세 (다음뉴스 ─ 불공정기사 모음)","contents":"프레시안","link":"https://v.daum.net/v/20220411080451828","retrieved":1649548800000},{"title":"국민의힘 공천 앞두고 안동시장 예비후보들 도덕성 자질 의혹 '무성' (다음뉴스 ─ 불공정기사 모음)","contents":"더팩트","link":"https://v.daum.net/v/20220328123224944","retrieved":1648425600000},{"title":"역대 당선 후보 족집게 인터뷰 美 타임지, 이번엔 이재명 기사 게재 (다음뉴스 ─ 불공정기사 모음)","contents":"대전일보","link":"https://v.daum.net/v/20220304164605385","retrieved":1646352000000},{"title":"민주 \"美 타임지, 이재명 유력 당선인으로 보고 있다\" (다음뉴스 ─ 불공정기사 모음)","contents":"헤럴드경제","link":"https://v.daum.net/v/20220304145003189","retrieved":1646352000000},{"title":"[노컷체크]윤석열, 우크라전쟁 똑바로 알고 있나 (다음뉴스 ─ 불공정기사 모음)","contents":"노컷뉴스","link":"https://v.daum.net/v/20220227040600591","retrieved":1645833600000},{"title":"러시아 침공에 李 \"우크라 초보정치인 책임\" 발언 부적절 논란 계속 (다음뉴스 ─ 불공정기사 모음)","contents":"조선일보","link":"https://v.daum.net/v/20220226132548340","retrieved":1645833600000},{"title":"러시아, 우크라 침공에..이재명 \"우리와 관계없지만, 주가는 하락\" (다음뉴스 ─ 불공정기사 모음)","contents":"조선비즈","link":"https://v.daum.net/v/20220224134204000","retrieved":1645660800000},{"title":"\"엽기 굿판에 윤석열 부부 연등 사진\"..국민의힘 \"마타도어\" (다음뉴스 ─ 불공정기사 모음)","contents":"한겨레","link":"https://v.daum.net/v/20220215235603286","retrieved":1644883200000},{"title":"외신 \"제2의 한국전쟁 가능성\"..푸틴-윤석열 어떤 관계길래 (다음뉴스 ─ 불공정기사 모음)","contents":"노컷뉴스","link":"https://v.daum.net/v/20220210114504025","retrieved":1644451200000}]}