{"title":"다음뉴스 ─ 문화 ─ 메이저","url":"https://news.daum.net/culture","favicon":"https://news.daum.net/favicon.ico","elements":[{"title":"\"인문의 가치 공유와 체득\"…'길 위의 인문학' 및 '지혜학교'","contents":"뉴스1","link":"https://v.daum.net/v/20240522095719858","retrieved":1716340807077},{"title":"당신의 술독…울고 웃으며 한국사 100년 ‘그때도 오늘’ [다시 보는 명대사③]","contents":"데일리안","link":"https://v.daum.net/v/20240522094554416","retrieved":1716340807078},{"title":"“‘흙수저’로 태어난 성공한 사람, 치매 발병 위험 가장 낮아”","contents":"동아일보","link":"https://v.daum.net/v/20240522094548413","retrieved":1716340807079},{"title":"“폐경 이후 여성, 고혈압 유병률 높고 합병증에 더 취약”","contents":"스포츠동아","link":"https://v.daum.net/v/20240522094141258","retrieved":1716340807080},{"title":"\"사고로 떠난 아들, 남은 가족은 그를 어떻게 추억할까\"…연극 'Be'","contents":"뉴스1","link":"https://v.daum.net/v/20240522094136253","retrieved":1716340807081},{"title":"음악극 '누가 이 사람을 모르시나요' 내달 27일 개막 공연","contents":"연합뉴스","link":"https://v.daum.net/v/20240522094058228","retrieved":1716340807082},{"title":"앞으로 식당서 \"소주 한잔·무알콜 맥주\" 주문 가능","contents":"한경비즈니스","link":"https://v.daum.net/v/20240522080404268","retrieved":1716340807084},{"title":"19세기 옛 모습 고스란히…주미대한제국공사관에 안내판 설치","contents":"연합뉴스","link":"https://v.daum.net/v/20240522093622042","retrieved":1716340807086},{"title":"기억력 정상이어도...‘이것’ 자주 발생하면 “치매 초기”","contents":"코메디닷컴","link":"https://v.daum.net/v/20240522093557018","retrieved":1716340807087},{"title":"관광공사, 내부통제 강화…올해 첫 내부통제위원회 개최","contents":"연합뉴스","link":"https://v.daum.net/v/20240522093145845","retrieved":1716340807090}]}