{"title":"다음뉴스 ─ 문화 ─ 메인뉴스","url":"https://news.daum.net/culture","favicon":"https://news.daum.net/favicon.ico","elements":[{"title":"때론 안달나게, 때론 벅차게…음율을 지배하는 자, 관객을 사로잡다","contents":"한국경제","link":"https://v.daum.net/v/20231116191414713","retrieved":1700129985340},{"title":"때론 녹아들게, 때론 강렬하게…피아노를 지배하는자, 무대를 찢다","contents":"한국경제","link":"https://v.daum.net/v/20231116191302688","retrieved":1700129985342},{"title":"깊고 묵직한 사운드가 객석을 파도처럼 덮쳤다","contents":"한국경제","link":"https://v.daum.net/v/20231116183602949","retrieved":1700129985343},{"title":"집에 구급상자 있다면, 지금 당장 체크할 것 6가지","contents":"코메디닷컴","link":"https://v.daum.net/v/20231116183110844","retrieved":1700129985345},{"title":"마이코플라스마 폐렴, 한 달 만에 2배 이상 급증","contents":"머니투데이","link":"https://v.daum.net/v/20231116175929859","retrieved":1700126323820},{"title":"항생제 '콧물약' 아니에요...항·필·제·사 왜 필요할까?","contents":"코메디닷컴","link":"https://v.daum.net/v/20231116170556930","retrieved":1700126323821}]}