{"title":"다음뉴스 ─ 문화 ─ 메인뉴스","url":"https://news.daum.net/culture","favicon":"https://news.daum.net/favicon.ico","elements":[{"title":"“100세인들은 낙천적인 성격”... 나는 왜 매사 부정적일까?","contents":"코메디닷컴","link":"https://v.daum.net/v/20240416145103284","retrieved":1713248595793},{"title":"\"사료 바꾸고 고양이 다리 절어\"…원인불명 질병에 떠는 집사들","contents":"머니투데이","link":"https://v.daum.net/v/20240416143621472","retrieved":1713248595795},{"title":"\"K-불교의 정수를 알린다\"…한국불교문화포털 서비스 개시","contents":"연합뉴스","link":"https://v.daum.net/v/20240416143952666","retrieved":1713248595796},{"title":"지능(IQ)이 유행하는 시대. 지능이 무엇인지 충분히 알고 계신가요? [이정민의 ‘내 마음의 건강검진’⑧]","contents":"데일리안","link":"https://v.daum.net/v/20240416140153916","retrieved":1713244838379},{"title":"눈 감았는데 빛이 번쩍…‘광시증’은 왜 생기는 걸까?","contents":"하이닥","link":"https://v.daum.net/v/20240416140113893","retrieved":1713244838383},{"title":"어린 아이들, 코로나19에 멀쩡한 이유 밝혀졌다","contents":"동아일보","link":"https://v.daum.net/v/20240416114912278","retrieved":1713244838384}]}