{"title":"다음뉴스 ─ 문화 ─ 메이저","url":"https://news.daum.net/culture","favicon":"https://news.daum.net/favicon.ico","elements":[{"title":"\"이제 겨우 자리 잡았나 싶었는데..영화인·주민 상의 없이 폐지 아쉬워\"","contents":"강원도민일보","link":"https://v.daum.net/v/20220826050135604","retrieved":1661462499498},{"title":"존재를 향한 시인의 울음 멈추지 않는다","contents":"강원도민일보","link":"https://v.daum.net/v/20220826050129602","retrieved":1661462499500},{"title":"[명경대] 삼척 죽서루","contents":"강원도민일보","link":"https://v.daum.net/v/20220826050101567","retrieved":1661462499504},{"title":"[장시우의 예술家 산책] 8. 오보이스트 그리고 지휘자 길주영","contents":"강원도민일보","link":"https://v.daum.net/v/20220826050042546","retrieved":1661462499504},{"title":"[편집기자가 운영하는 펀·집·숍] 물건 아닌 가족으로, 새 이름을 지어주세요","contents":"강원도민일보","link":"https://v.daum.net/v/20220826050035540","retrieved":1661459097313},{"title":"홍천군 가로수 의도적 고사 '독살범 찾기' 총력","contents":"강원도민일보","link":"https://v.daum.net/v/20220826050035538","retrieved":1661459097314},{"title":"단풍 명당, 제주사람들도 엄지척..가을날 유독 아름다운 5곳","contents":"중앙일보","link":"https://v.daum.net/v/20220826050035539","retrieved":1661459097315},{"title":"마운드의 '학폭'을 복기해야 하는 이유 [강소희·서효인의 작전타임]","contents":"한국일보","link":"https://v.daum.net/v/20220826043245397","retrieved":1661459097325},{"title":"\"미술관 아니에요\" 아홉 겹 벽의 마술, 미로성 닮은 '집 속의 집'","contents":"한국일보","link":"https://v.daum.net/v/20220826043120381","retrieved":1661459097327},{"title":"3000만원 넘는 '예술 책'· 희귀본..미술 애호가 사로잡을 도서관 문 열어","contents":"한국일보","link":"https://v.daum.net/v/20220826043106380","retrieved":1661459097328}]}