{"title":"다음뉴스 ─ IT ─ 메인뉴스","url":"https://news.daum.net/digital","favicon":"https://news.daum.net/favicon.ico","elements":[{"title":"[누리호 2차발사 D-1]②8개월만에 재도전..1차 발사와 달라진 점","contents":"연합뉴스","link":"https://v.daum.net/v/20220615051555001","retrieved":1655238322917},{"title":"[누리호 2차발사 D-1]①오늘 발사대로 이동..하늘 향해 우뚝","contents":"연합뉴스","link":"https://v.daum.net/v/20220615051552000","retrieved":1655238322918},{"title":"中 기업이 규제에 맞서는 법.. 사교육업체가 영어로 식자재 판매","contents":"조선일보","link":"https://v.daum.net/v/20220615030502162","retrieved":1655234384988},{"title":"누리호, 16분 7초의 우주 비행..5번의 고비 넘겨야","contents":"YTN","link":"https://v.daum.net/v/20220615021908865","retrieved":1655227615530},{"title":"네·카·쿠 '자사 상품 몰아주기' 규제냐 자율이냐","contents":"중앙일보","link":"https://v.daum.net/v/20220615000431189","retrieved":1655220288632},{"title":"\"너무 못생겼다\" 애플 사지, 삼성 것 누가 사? 혹평 곤혹","contents":"헤럴드경제","link":"https://v.daum.net/v/20220614195132240","retrieved":1655213889893}]}