{"title":"다음뉴스 ─ IT ─ 메이저","url":"https://news.daum.net/digital","favicon":"https://news.daum.net/favicon.ico","elements":[{"title":"금융권 진출에… 알뜰폰, 힘겨운 생존 경쟁","contents":"머니S","link":"https://v.daum.net/v/20230611064106681","retrieved":1686489834543},{"title":"유명무실 단통법 사라질까… \"알뜰폰 잠식\" VS \"단말기값 인하\"","contents":"머니S","link":"https://v.daum.net/v/20230611065106748","retrieved":1686489834545},{"title":"알뜰폰이 뭐예요… 통신 3사보다 좋을까","contents":"머니S","link":"https://v.daum.net/v/20230611063119539","retrieved":1686486769203},{"title":"서울시, 가상화 기술로 3만1000여개 공공 와이파이 관리...언제 어디서나 품질관리 가능","contents":"전자신문","link":"https://v.daum.net/v/20230611170113974","retrieved":1686486769205},{"title":"AI 위협에 기본소득 도입?…알고보면 내 정보값","contents":"연합뉴스TV","link":"https://v.daum.net/v/20230611173211469","retrieved":1686478762607},{"title":"훼손 위기 대구 팔현습지서 멸종위기 ‘수리부엉이’ 한쌍 발견","contents":"경향신문","link":"https://v.daum.net/v/20230611172457339","retrieved":1686478762607},{"title":"한 치 앞 안 보여도 ‘AI 로봇 잠수사’가 찾아냅니다","contents":"경향신문","link":"https://v.daum.net/v/20230611205003562","retrieved":1686496675381},{"title":"글로벌 기업 10곳 중 7곳은 산업 인프라 해킹에 노출","contents":"아이뉴스24","link":"https://v.daum.net/v/20230611130035329","retrieved":1686496675382},{"title":"[테크&포커스] \"저작권 침해\" vs \"작업생산성 향상\"… 뜨거운 감자 된 AI웹툰","contents":"디지털타임스","link":"https://v.daum.net/v/20230611181030114","retrieved":1686500715560},{"title":"사외이사 후보 정한 KT… CEO선임 속도","contents":"디지털타임스","link":"https://v.daum.net/v/20230611143912805","retrieved":1686500715562}]}