{"title":"다음뉴스 ─ 경제 ─ 메이저","url":"https://news.daum.net/economic","favicon":"https://news.daum.net/favicon.ico","elements":[{"title":"'준강남'이라더니 다시 '20억 클럽'…\"전세는 부르는 게 값\"","contents":"한국경제","link":"https://v.daum.net/v/20230915065301831","retrieved":1694729756467},{"title":"실적 이 지경인데 CEO는 'DJ 파티'…위기의 골드만삭스 [나수지의 뉴욕리포트]","contents":"한국경제","link":"https://v.daum.net/v/20230915064601763","retrieved":1694729756468},{"title":"자동차세, 배기량 대신 ‘차량 가격’ 기준으로…문제없나","contents":"아시아경제","link":"https://v.daum.net/v/20230915064123693","retrieved":1694729756470},{"title":"[Why&Next]폐배터리 재활용 기업 M&A 각축전‥600조 폐배터리 전쟁","contents":"아시아경제","link":"https://v.daum.net/v/20230915064024677","retrieved":1694729756472},{"title":"'높이 규제' 청량리동 19 일대 35층·843세대 아파트단지로 '확' 바뀐다","contents":"뉴스1","link":"https://v.daum.net/v/20230915064002667","retrieved":1694729756474},{"title":"\"中 침공보다 '이 사람' 부족이 더 위협적\" TSMC 회장의 말","contents":"파이낸셜뉴스","link":"https://v.daum.net/v/20230915063327581","retrieved":1694729756477},{"title":"한국서 집 사려면 '26년치' 월급 모아야…이런 주요국은 없다","contents":"뉴스1","link":"https://v.daum.net/v/20230915063231557","retrieved":1694729756479},{"title":"'큰손' 중국에 뒤통수 안돼…유럽·美·동남아 뚫는 석화업계","contents":"뉴스1","link":"https://v.daum.net/v/20230915063201555","retrieved":1694729756483},{"title":"美 8월 CPI 고비 넘자 나아진 ‘코인 투심’…반등 이뤄질까","contents":"아시아경제","link":"https://v.daum.net/v/20230915063033545","retrieved":1694729756485},{"title":"현대차 아이오닉 5 N 테크데이 개최 \"빠르면서도 즐거운 차량을 추구한다\"","contents":"한국일보","link":"https://v.daum.net/v/20230915063003517","retrieved":1694729756487}]}