{"title":"다음뉴스 ─ 경제 ─ 메이저","url":"https://news.daum.net/economic","favicon":"https://news.daum.net/favicon.ico","elements":[{"title":"“외제차 ‘아빠 찬스’ 막차 타자”…고가 법인차 등록 58% 증가, 왜?","contents":"매일경제","link":"https://v.daum.net/v/20240114194800139","retrieved":1705235468592},{"title":"\"한국에도 일론 머스크 나오게…기업가정신, 정규교과에 넣자\"","contents":"매일경제","link":"https://v.daum.net/v/20240114180300989","retrieved":1705235468593},{"title":"LG엔솔·GM 합작 배터리 2공장, 이르면 1분기 가동","contents":"전자신문","link":"https://v.daum.net/v/20240114163105098","retrieved":1705235468594},{"title":"매매는 하락, 전세는 상승…주거사다리 전세시장 '적색등'","contents":"대전일보","link":"https://v.daum.net/v/20240114191953854","retrieved":1705235468596},{"title":"\"타다·로톡사태 반복되면 혁신 위축…국민 편익 우선해야\"","contents":"한국경제","link":"https://v.daum.net/v/20240114191101789","retrieved":1705235468598},{"title":"전국 262만 가구 재건축 기대하지만… ‘실거주 의무 폐지’ 시즌2 될 수도","contents":"국민일보","link":"https://v.daum.net/v/20240114190911768","retrieved":1705235468601},{"title":"'민생 토론회'서 발표되는 정책들, 민생 살리기인가 총선용인가","contents":"더스쿠프","link":"https://v.daum.net/v/20240114190443728","retrieved":1705230902055},{"title":"굵직한 경제정책 쏟아내지만 법률개정 뒷전…‘총선용’ 비판","contents":"국민일보","link":"https://v.daum.net/v/20240114190111688","retrieved":1705230902057},{"title":"한미약품 장남 반발…\"주주 소통없는 독단적 결정\"","contents":"한국경제","link":"https://v.daum.net/v/20240114185505605","retrieved":1705230902061},{"title":"안전진단만 없애면 재건축 ‘순풍’? 사업성 없으면 ‘무풍’","contents":"한겨레","link":"https://v.daum.net/v/20240114183528425","retrieved":1705230902066}]}