{"title":"다음뉴스 ─ 국제 ─ 메인뉴스","url":"https://news.daum.net/foreign","favicon":"https://news.daum.net/favicon.ico","elements":[{"title":"재벌 7명 사망 초호화 요트 침몰 미스터리…선장이 살인 용의자","contents":"문화일보","link":"https://v.daum.net/v/20240827220431750","retrieved":1724765016002},{"title":"프랑스 전력공사도 ‘한수원 체코 수주’ 발목... 美·佛 합동 공세","contents":"조선비즈","link":"https://v.daum.net/v/20240827214252436","retrieved":1724765016002},{"title":"트럼프, 또 꺼낸 '방위비 분담금'…\"GDP 2%는 도둑질, 3% 되야\"","contents":"MBN","link":"https://v.daum.net/v/20240827193018775","retrieved":1724765016004},{"title":"“퇴근 후 직장상사 전화, 거부하세요”…어긴 기업엔 ‘벌금’ 8500만원!","contents":"헤럴드경제","link":"https://v.daum.net/v/20240827220230712","retrieved":1724765016005},{"title":"탈북민 15명 필사의 탈출 현장 포착…\"중국서 체포\"","contents":"MBN","link":"https://v.daum.net/v/20240827193418905","retrieved":1724765016007},{"title":"러시아, 군인 사상자만 50만 명…평균 연봉 5배 7천만 원에 모병 광고","contents":"MBN","link":"https://v.daum.net/v/20240827193218841","retrieved":1724765016008}]}