{"title":"다음뉴스 ─ 국제 ─ 메인뉴스","url":"https://news.daum.net/foreign","favicon":"https://news.daum.net/favicon.ico","elements":[{"title":"\"이 M&A 반대야\"…'최강동맹' 일본에도 쉽게 주지 않는 미국","contents":"머니투데이","link":"https://v.daum.net/v/20240503171339080","retrieved":1714724490864},{"title":"\"한·일 관계 개선 혜택 맛봐야 더 협력…출입국 우대, 교통카드 호환부터\"","contents":"중앙일보","link":"https://v.daum.net/v/20240503170310814","retrieved":1714724490865},{"title":"美 반전 시위로 체포된 학생 2000명 넘어… 강경 진압 논란도","contents":"동아일보","link":"https://v.daum.net/v/20240503170223767","retrieved":1714724490866},{"title":"'오리고 잘라 만든' 내수 진작용 중국 노동절 닷새 연휴... 관광 수요는 폭발","contents":"한국일보","link":"https://v.daum.net/v/20240503170048709","retrieved":1714724490868},{"title":"미국·중국발 호재까지 업은 홍콩, 9거래일 연속 상승 [Asia마감]","contents":"머니투데이","link":"https://v.daum.net/v/20240503165637573","retrieved":1714724490870},{"title":"이란, '이스라엘 연관' 선원 석방…선박은 계속 억류","contents":"뉴스1","link":"https://v.daum.net/v/20240503164925390","retrieved":1714724490872}]}