{"title":"다음뉴스 ─ 국제 ─ 메이저","url":"https://news.daum.net/foreign","favicon":"https://news.daum.net/favicon.ico","elements":[{"title":"美, 대만에 무기수출 또 승인","contents":"헤럴드경제","link":"https://v.daum.net/v/20220208112000699","retrieved":1644297531010},{"title":"[올림픽] 중국, 홈 텃세 시선에 \"금메달 개수 목표 아니다\"","contents":"연합뉴스","link":"https://v.daum.net/v/20220208102829220","retrieved":1644297531011},{"title":"\"쇼트트랙 판정 항의 못 받아들여\" 심판 감싼 ISU(종합)","contents":"서울신문","link":"https://v.daum.net/v/20220208103604579","retrieved":1644297531012},{"title":"나토 두갈래 동시회담..\"러시아 강공에 분열상·봉합노력 노출\"","contents":"연합뉴스","link":"https://v.daum.net/v/20220208121357060","retrieved":1644297531013},{"title":"강창일 \"2·8 독립선언 정신 계승해 한일관계 정상화\"","contents":"연합뉴스","link":"https://v.daum.net/v/20220208120906922","retrieved":1644294334869},{"title":"이탈리아, 야외 마스크 11일 해제..단계적 '위드 코로나'","contents":"뉴시스","link":"https://v.daum.net/v/20220208120852918","retrieved":1644294334872},{"title":"유럽 정상들 긴박한 회담..'대화 창구'는 열었다","contents":"아시아경제","link":"https://v.daum.net/v/20220208120450785","retrieved":1644294334873},{"title":"우크라 사태 '해결사'로 떠오른 마크롱..푸틴 \"가능성 봤다\"","contents":"이데일리","link":"https://v.daum.net/v/20220208104933194","retrieved":1644294334874},{"title":"[영상] 23살 어린 부인이 뒤에서 조종?..영국 총리가 위기몰린 배경은","contents":"연합뉴스","link":"https://v.daum.net/v/20220208115809498","retrieved":1644297531019},{"title":"IS 수괴 제거한 美, 다음 목표는 이놈..'현상금 120억' 걸었다","contents":"중앙일보","link":"https://v.daum.net/v/20220208115535419","retrieved":1644294334875}]}