{"title":"다음뉴스 ─ 홈","url":"https://news.daum.net/","favicon":"https://news.daum.net/favicon.ico","elements":[{"title":"실거래가, 고시가보다 2억 이상 ‘뚝뚝’…커지는 깡통주택 공포","contents":"경제","link":"https://v.daum.net/v/20230130060325868","retrieved":1675034336374},{"title":"한국투자저축은행 유동성 '빨간불'…규제 마지노선 '붕괴'","contents":"경제","link":"https://v.daum.net/v/20230130060014721","retrieved":1675034336375},{"title":"박근혜 전 대통령 대구 달성 사저 입주 첫 생일…보수단체 ‘축하집회’","contents":"사회","link":"https://v.daum.net/v/20230130075707204","retrieved":1675034336381},{"title":"北 나토 사무총장 방한에 맹비난...\"'아시아판 나토'발 신냉전 우려\"","contents":"정치","link":"https://v.daum.net/v/20230130080443364","retrieved":1675034336381},{"title":"\"월급 26%가 연금 보험료로?\"…2055년 청년들에게 닥칠 일","contents":"사회","link":"https://v.daum.net/v/20230130080002241","retrieved":1675034336381},{"title":"‘평창 면온 -17.5도’ 맹추위…영동·남부산지 ‘대기 건조’","contents":"사회","link":"https://v.daum.net/v/20230130075444168","retrieved":1675034336383},{"title":"신구 윤핵관 상반된 행보…권성동 ‘지역’ 유상범 ‘수도권’","contents":"정치","link":"https://v.daum.net/v/20230130050103159","retrieved":1675034336385},{"title":"‘퐁당퐁당’ 응급실·원장 없는 병원… 의료공백 현실화","contents":"문화","link":"https://v.daum.net/v/20230130050105166","retrieved":1675034336387},{"title":"‘10년 답보’ 원주 부론산단, 반도체 클러스터 조성 연쇄 차질","contents":"정치","link":"https://v.daum.net/v/20230130050112183","retrieved":1675034336388},{"title":"[저무는 킹달러]②지금 사도 되나…금·달러 투자 전략은","contents":"경제","link":"https://v.daum.net/v/20230130061058939","retrieved":1675034336389},{"title":"14억 중국, 인구 줄어서 고민…미중 경쟁에 불리해지나","contents":"국제","link":"https://v.daum.net/v/20230130070507544","retrieved":1675034336391},{"title":"걸어다닐 수도 없고…버스·지하철·택시 줄줄이 다 오른다","contents":"사회","link":"https://v.daum.net/v/20230130060520891","retrieved":1675034336392},{"title":"中 비자 발급, 日에만 재개하고 韓 안 풀어준 이유","contents":"국제","link":"https://v.daum.net/v/20230130080858429","retrieved":1675034336393},{"title":"소득 줄고 난방비 늘어… 1분기 유독 ‘팍팍한 서민 살림살이’","contents":"경제","link":"https://v.daum.net/v/20230130060318866","retrieved":1675034336398},{"title":"[소양강댐의 빛과 그림자] 4. 소양강댐 건설 비화","contents":"속보","link":"https://v.daum.net/v/20230130050026102","retrieved":1675034336400},{"title":"마트 갔는데 과태료 10만원?…혹시 마트 내 '약국' 가셨나요?","contents":"문화","link":"https://v.daum.net/v/20230130080605393","retrieved":1675034336401},{"title":"해진 양말 들어 보인 안철수…“모으고 모아 1500억 기부”","contents":"정치","link":"https://v.daum.net/v/20230130074124982","retrieved":1675034336404},{"title":"일제강점기 시가전 벌인 김상옥 의사 순국 100주년 기념식","contents":"정치","link":"https://v.daum.net/v/20230130075006097","retrieved":1675034336405},{"title":"\"명품 한정판 핸드백 다 있다\"…도피중 홍콩재벌 26억짜리 경매","contents":"국제","link":"https://v.daum.net/v/20230130073228873","retrieved":1675034336407},{"title":"최강한파는 물러가고…전국 대체로 맑은 날씨","contents":"사회","link":"https://v.daum.net/v/20230130073900948","retrieved":1675034336409}]}