{"title":"다음뉴스 ─ 정치 ─ 메인뉴스","url":"https://news.daum.net/politics","favicon":"https://news.daum.net/favicon.ico","elements":[{"title":"'읽씹' 논란, '특검' 불 지피는 巨野…\"제2의 국정농단\"","contents":"노컷뉴스","link":"https://v.daum.net/v/20240708051200598","retrieved":1720383501375},{"title":"[단독] 정부, 미복귀 전공의 1만명 불이익 안 준다","contents":"조선일보","link":"https://v.daum.net/v/20240708050615557","retrieved":1720383501377},{"title":"어르신들 택시 타기 쉽게… ‘백세콜’로 배차 안내 제공","contents":"서울신문","link":"https://v.daum.net/v/20240708050258489","retrieved":1720383501378},{"title":"尹, 오늘 '안보 순방' 출국...'美 인태 사령부' 방문","contents":"YTN","link":"https://v.daum.net/v/20240708050413528","retrieved":1720383501380},{"title":"“은평 문화벨트 레벨 업… 서울 유일 편백숲은 힐링 공간으로”[민선 8기 2년, 서울 단체장에게 묻다]","contents":"서울신문","link":"https://v.daum.net/v/20240708050256488","retrieved":1720383501381},{"title":"한동훈 “변화는 반발 있기 마련… 단합 위해 네거티브 내가 참겠다” [與 당권주자 인터뷰 ②]","contents":"세계일보","link":"https://v.daum.net/v/20240708050215454","retrieved":1720383501382}]}