{"title":"다음뉴스 ─ 정치 ─ 메인뉴스","url":"https://news.daum.net/politics","favicon":"https://news.daum.net/favicon.ico","elements":[{"title":"윤핵관 분화? 추대론 역풍?..국민의힘 놀래킨 이용호의 '돌풍'","contents":"데일리안","link":"https://v.daum.net/v/20220920002057262","retrieved":1663601247940},{"title":"英 여왕 조문외교 마친 尹 \"자유·평화 향한 헌신 잊지 않을 것\"","contents":"뉴시스","link":"https://v.daum.net/v/20220920001842253","retrieved":1663601247940},{"title":"군 '팬티 예산' 논쟁 불붙인 이재명, 與 '팬티 업체 쌍방울'로 되치기","contents":"데일리안","link":"https://v.daum.net/v/20220920001430226","retrieved":1663601247943},{"title":"\"한국 가고 싶습니다\" 尹 만난 각국 정상들 방한 요청 쇄도","contents":"노컷뉴스","link":"https://v.daum.net/v/20220920000900169","retrieved":1663601247950},{"title":"한덕수 \"영빈관, 신문 보고 알았다\" 야당 \"책임자 문책해야\"","contents":"중앙일보","link":"https://v.daum.net/v/20220920000737162","retrieved":1663601247950},{"title":"'국정농단 게이트' 서막..최순실, 언론 전면에 등장[그해 오늘]","contents":"이데일리","link":"https://v.daum.net/v/20220920000309077","retrieved":1663601247950}]}