{"title":"다음뉴스 ─ 정치 ─ 메이저","url":"https://news.daum.net/politics","favicon":"https://news.daum.net/favicon.ico","elements":[{"title":"동두천시, 경기도 공공의료원 유치 총력…캠페인 시작","contents":"이데일리","link":"https://v.daum.net/v/20240603160450351","retrieved":1717399083840},{"title":"尹 \"140억 배럴 석유·가스 가능성...시추계획 승인\"","contents":"YTN","link":"https://v.daum.net/v/20240603160709454","retrieved":1717399083840},{"title":"가짜 정신질환 의심 제대 병사 5000여명, 손 놓은 국방부","contents":"중앙일보","link":"https://v.daum.net/v/20240603160354323","retrieved":1717399083840},{"title":"北 오물 풍선에 네 탓 공방...\"文 굴종\" vs \"尹 방치\"","contents":"YTN","link":"https://v.daum.net/v/20240603160419335","retrieved":1717399083841},{"title":"[노컷브이]국힘 지도부 앞에서 '채 상병 특검' 반기 든 김용태","contents":"노컷뉴스","link":"https://v.daum.net/v/20240603160305274","retrieved":1717399083843},{"title":"개보위, AI 기술 활용 '자동화된 결정 권리' 현장의견 청취","contents":"뉴스1","link":"https://v.daum.net/v/20240603160153193","retrieved":1717399083844},{"title":"지방의원 '보좌관제' 도입될까…'개인 비서화' 우려에 여론 싸늘","contents":"연합뉴스","link":"https://v.daum.net/v/20240603160126171","retrieved":1717399083846},{"title":"역사 속 옥포대첩, 축제로 화려한 부활","contents":"한국일보","link":"https://v.daum.net/v/20240603160112162","retrieved":1717399083847},{"title":"與, 김정숙 특검으로 맞불…“文정부 권력형 비리”","contents":"이데일리","link":"https://v.daum.net/v/20240603160104156","retrieved":1717399083848},{"title":"소 키우던 소년에서 '박사'로... 9급공무원, 신화를 쓰다","contents":"오마이뉴스","link":"https://v.daum.net/v/20240603155701959","retrieved":1717399083849}]}