{"title":"다음 뉴스 ─ 랭킹 ─ 연령별 ─ 50대이상 남성","url":"https://news.daum.net/ranking/age","favicon":"https://news.daum.net/ranking/favicon.ico","elements":[{"title":"스피커폰 인사 윤석열에..청년들 \"정신 못차렸다\"","contents":"뉴시스","link":"https://v.daum.net/v/20220105181900690","retrieved":1641381506610},{"title":"'이재명 손배 소송' 김부선, 아주대병원 의료진 증인 신청","contents":"연합뉴스","link":"https://v.daum.net/v/20220105182342786","retrieved":1641381506614},{"title":"국민의힘 사무총장 권영세 겸임..정책본부장 원희룡(종합)","contents":"연합뉴스","link":"https://v.daum.net/v/20220105184805163","retrieved":1641381506615},{"title":"숨진 청년 이수철씨 원룸엔 이력서 150장만 '수북'","contents":"국민일보","link":"https://v.daum.net/v/20220105183346986","retrieved":1641381506617},{"title":"\"2년간 도망다녔는데\"..식기세척기 숨어있다 잡힌 보이스피싱범","contents":"서울신문","link":"https://v.daum.net/v/20220105172606165","retrieved":1641378224460}]}