{"title":"다음뉴스 ─ 사회 ─ 메인뉴스","url":"https://news.daum.net/society","favicon":"https://news.daum.net/favicon.ico","elements":[{"title":"경북소방 \"예천 고평교서 실종 해병대원 발견해 인양 중\"","contents":"한국경제","link":"https://v.daum.net/v/20230719233003022","retrieved":1689779873388},{"title":"[단독] '면직' 징계 두 번 받고도 복직한 공공기관 고위 간부","contents":"한국일보","link":"https://v.daum.net/v/20230720001009709","retrieved":1689779873395},{"title":"사유지 견인 불가 ‘무개념 주차’ 불편은 이웃 몫","contents":"강원도민일보","link":"https://v.daum.net/v/20230720000621641","retrieved":1689779873398},{"title":"민선7기 현안사업 고발·감사…전-현 지방정부 충돌","contents":"강원도민일보","link":"https://v.daum.net/v/20230720000618638","retrieved":1689779873402},{"title":"“총선 전석확보 제가 가진 책임” 필승 다짐","contents":"강원도민일보","link":"https://v.daum.net/v/20230720000543603","retrieved":1689779873406},{"title":"국힘 도당 ‘박정하 체제’ 출범 “정책으로 승부하는 정당으로”","contents":"강원도민일보","link":"https://v.daum.net/v/20230720000545604","retrieved":1689779873409}]}