{"title":"다음뉴스 ─ 사회 ─ 메이저","url":"https://news.daum.net/society","favicon":"https://news.daum.net/favicon.ico","elements":[{"title":"저출산·고령화에 어린이집이 요양원으로…'인구소멸 1호' 경고까지","contents":"SBS","link":"https://v.daum.net/v/20240102210908119","retrieved":1704198718399},{"title":"아궁이 앞 전신화상 50대 시신..경찰 수사 \"연탄 교체하다..\"","contents":"kbc광주방송","link":"https://v.daum.net/v/20240102205002823","retrieved":1704198718400},{"title":"화재 속 홀로 탈출 못 한 5살 아이…'돌봄 강화' 숙제로","contents":"SBS","link":"https://v.daum.net/v/20240102210606067","retrieved":1704198718402},{"title":"사건 현장에 경찰관 41명 있었지만…'구멍난 경호' 3가지 이유","contents":"JTBC","link":"https://v.daum.net/v/20240102210312023","retrieved":1704198718403},{"title":"구자은·장재훈·김익환 “용처럼 날아오를 것” [CEO 라운지]","contents":"매경이코노미","link":"https://v.daum.net/v/20240102210300010","retrieved":1704198718405},{"title":"이번에는 국회의사당역 낙서 훼손…처벌 강화 목소리","contents":"MBN","link":"https://v.daum.net/v/20240102193844551","retrieved":1704198718407},{"title":"새해에도 반복된 낙하산 부군수..전공노 반발 \"편법과 반칙\"","contents":"CJB청주방송","link":"https://v.daum.net/v/20240102205531906","retrieved":1704198718408},{"title":"충북 각 기관 새해 업무 돌입..기관장에게 듣는 새 각오와 다짐","contents":"CJB청주방송","link":"https://v.daum.net/v/20240102205413886","retrieved":1704198718411},{"title":"\"거동 불편해 대피 못해\"…군포시 아파트 화재로 50대 가장 사망","contents":"SBS","link":"https://v.daum.net/v/20240102205404880","retrieved":1704198718411},{"title":"‘탈공무원’ 막아라…저연차 보수 최대 6% 인상","contents":"경향신문","link":"https://v.daum.net/v/20240102205343868","retrieved":1704198718412}]}