{"title":"다음뉴스 ─ 사회 ─ 메이저","url":"https://news.daum.net/society","favicon":"https://news.daum.net/favicon.ico","elements":[{"title":"'시골에만 있는 게 아니야'…경기도 도시지역에도 빈집 1천650호","contents":"연합뉴스","link":"https://v.daum.net/v/20230528080426433","retrieved":1685229598384},{"title":"개통 10년 넘긴 의정부경전철…반복되는 전동차 급정거","contents":"연합뉴스","link":"https://v.daum.net/v/20230528080318419","retrieved":1685229598388},{"title":"[일문Chat답] 연봉 1억도 겁내는 결혼…챗GPT \"'남자는 집' 언젯적 얘기인지\"","contents":"MBN","link":"https://v.daum.net/v/20230528080304406","retrieved":1685229598390},{"title":"'교육자치 강화하는데…' 양양군 숙원인 교육지원청 설립 언제쯤","contents":"연합뉴스","link":"https://v.daum.net/v/20230528080227390","retrieved":1685229598391},{"title":"'임용 적체' 해소 대책 요원…\"대기자 방치 안 돼\"[임용대란②]","contents":"뉴시스","link":"https://v.daum.net/v/20230528080204367","retrieved":1685229598392},{"title":"'돈봉투' 체포동의안 변수 '이재명 사과'…심사 열리면 '증거인멸'","contents":"뉴시스","link":"https://v.daum.net/v/20230528080203366","retrieved":1685229598393},{"title":"35년 만에 부활한 ‘울산공업축제’···소달구지부터 친환경자동차까지 시가지 퍼레이드 ‘백미’[주말엔]","contents":"경향신문","link":"https://v.daum.net/v/20230528080157355","retrieved":1685229598395},{"title":"\"학폭위 처분 과해\" 소송 건 가해자…시간끌기 '최장 26개월'","contents":"머니투데이","link":"https://v.daum.net/v/20230528080115347","retrieved":1685229598395},{"title":"[주목, 이주의 재판] '도이치모터스 주가조작' 권오수 2심 첫 재판","contents":"뉴스1","link":"https://v.daum.net/v/20230528080111344","retrieved":1685229598397},{"title":"\"동요할까 걱정\"…전세사기 5번째 사망에 심리회복도 문제","contents":"연합뉴스","link":"https://v.daum.net/v/20230528080031321","retrieved":1685229598404}]}